{"37558":{"id":37558,"level":379,"players":1500,"active_players":1076,"clicks":"8428054","abilities":"2635","status":2,"timestamp":1434213146,"timestamp_game_start":1434211809,"timestamp_level_start":1434213143},"37554":{"id":37554,"level":179,"players":1500,"active_players":906,"clicks":"4475498","abilities":"1134","status":2,"timestamp":1434213146,"timestamp_game_start":1434211846,"timestamp_level_start":1434213144},"37530":{"id":37530,"level":0,"players":2,"active_players":46,"clicks":null,"abilities":null,"status":3,"timestamp":1434211234,"timestamp_game_start":1434211234,"timestamp_level_start":1434211234},"37523":{"id":37523,"level":0,"players":805,"active_players":347,"clicks":"33217","abilities":null,"status":3,"timestamp":1434211201,"timestamp_game_start":1434211171,"timestamp_level_start":1434211171},"37517":{"id":37517,"level":0,"players":0,"active_players":58,"clicks":null,"abilities":null,"status":3,"timestamp":1434211218,"timestamp_game_start":1434211218,"timestamp_level_start":1434211218},"37592":{"id":37592,"level":103,"players":998,"active_players":495,"clicks":"2269538","abilities":"548","status":2,"timestamp":1434213147,"timestamp_game_start":1434212065,"timestamp_level_start":1434213139},"37633":{"id":37633,"level":75,"players":1007,"active_players":525,"clicks":"1527569","abilities":"293","status":2,"timestamp":1434213147,"timestamp_game_start":1434212387,"timestamp_level_start":1434213146},"37680":{"id":37680,"level":22,"players":1005,"active_players":591,"clicks":"559275","abilities":"40","status":2,"timestamp":1434213147,"timestamp_game_start":1434212811,"timestamp_level_start":1434213139},"37540":{"id":37540,"level":0,"players":0,"active_players":206,"clicks":null,"abilities":null,"status":3,"timestamp":1434211284,"timestamp_game_start":1434211284,"timestamp_level_start":1434211284},"37603":{"id":37603,"level":121,"players":1060,"active_players":536,"clicks":"2741395","abilities":"635","status":2,"timestamp":1434213147,"timestamp_game_start":1434212063,"timestamp_level_start":1434213144},"37686":{"id":37686,"level":32,"players":990,"active_players":555,"clicks":"799666","abilities":"80","status":2,"timestamp":1434213147,"timestamp_game_start":1434212740,"timestamp_level_start":1434213145},"37544":{"id":37544,"level":0,"players":0,"active_players":37,"clicks":null,"abilities":null,"status":3,"timestamp":1434211290,"timestamp_game_start":1434211290,"timestamp_level_start":1434211290},"37591":{"id":37591,"level":103,"players":1009,"active_players":512,"clicks":"2115224","abilities":"528","status":2,"timestamp":1434213147,"timestamp_game_start":1434212100,"timestamp_level_start":1434213143},"37552":{"id":37552,"level":168,"players":1229,"active_players":668,"clicks":"4399403","abilities":"956","status":2,"timestamp":1434213147,"timestamp_game_start":1434211820,"timestamp_level_start":1434213143},"37581":{"id":37581,"level":170,"players":1190,"active_players":632,"clicks":"4389140","abilities":"984","status":2,"timestamp":1434213147,"timestamp_game_start":1434211844,"timestamp_level_start":1434213145},"37578":{"id":37578,"level":160,"players":1186,"active_players":696,"clicks":"4306414","abilities":"1041","status":2,"timestamp":1434213147,"timestamp_game_start":1434211822,"timestamp_level_start":1434213141},"37600":{"id":37600,"level":141,"players":1086,"active_players":610,"clicks":"3575465","abilities":"718","status":2,"timestamp":1434213147,"timestamp_game_start":1434211981,"timestamp_level_start":1434213141},"37611":{"id":37611,"level":117,"players":1020,"active_players":512,"clicks":"2523426","abilities":"520","status":2,"timestamp":1434213147,"timestamp_game_start":1434212080,"timestamp_level_start":1434213141},"37532":{"id":37532,"level":0,"players":0,"active_players":51,"clicks":null,"abilities":null,"status":3,"timestamp":1434211264,"timestamp_game_start":1434211264,"timestamp_level_start":1434211264},"37566":{"id":37566,"level":108,"players":1066,"active_players":536,"clicks":"2307482","abilities":"537","status":2,"timestamp":1434213147,"timestamp_game_start":1434212120,"timestamp_level_start":1434213147},"37692":{"id":37692,"level":21,"players":990,"active_players":601,"clicks":"554591","abilities":"30","status":2,"timestamp":1434213147,"timestamp_game_start":1434212853,"timestamp_level_start":1434213145},"37599":{"id":37599,"level":103,"players":1013,"active_players":487,"clicks":"2544933","abilities":"500","status":2,"timestamp":1434213147,"timestamp_game_start":1434212088,"timestamp_level_start":1434213143},"37673":{"id":37673,"level":30,"players":990,"active_players":569,"clicks":"747048","abilities":"72","status":2,"timestamp":1434213147,"timestamp_game_start":1434212746,"timestamp_level_start":1434213141},"37597":{"id":37597,"level":112,"players":1050,"active_players":545,"clicks":"2421777","abilities":"535","status":2,"timestamp":1434213147,"timestamp_game_start":1434212072,"timestamp_level_start":1434213142},"37685":{"id":37685,"level":22,"players":988,"active_players":596,"clicks":"631595","abilities":"48","status":2,"timestamp":1434213147,"timestamp_game_start":1434212823,"timestamp_level_start":1434213139},"37529":{"id":37529,"level":0,"players":0,"active_players":193,"clicks":null,"abilities":null,"status":3,"timestamp":1434211304,"timestamp_game_start":1434211304,"timestamp_level_start":1434211304},"37639":{"id":37639,"level":82,"players":1023,"active_players":545,"clicks":"7276598","abilities":"308","status":2,"timestamp":1434213147,"timestamp_game_start":1434212385,"timestamp_level_start":1434213141},"37672":{"id":37672,"level":23,"players":983,"active_players":568,"clicks":"547656","abilities":"48","status":2,"timestamp":1434213147,"timestamp_game_start":1434212842,"timestamp_level_start":1434213145},"37555":{"id":37555,"level":158,"players":1095,"active_players":581,"clicks":"11333355","abilities":"829","status":2,"timestamp":1434213147,"timestamp_game_start":1434211843,"timestamp_level_start":1434213145},"37656":{"id":37656,"level":61,"players":1003,"active_players":534,"clicks":"1252429","abilities":"202","status":2,"timestamp":1434213147,"timestamp_game_start":1434212453,"timestamp_level_start":1434213146},"37606":{"id":37606,"level":114,"players":1059,"active_players":529,"clicks":"3028555","abilities":"560","status":2,"timestamp":1434213147,"timestamp_game_start":1434211983,"timestamp_level_start":1434213141},"37586":{"id":37586,"level":159,"players":1139,"active_players":634,"clicks":"3510995","abilities":"958","status":2,"timestamp":1434213147,"timestamp_game_start":1434211840,"timestamp_level_start":1434213144},"37683":{"id":37683,"level":29,"players":1002,"active_players":540,"clicks":"650038","abilities":"62","status":2,"timestamp":1434213147,"timestamp_game_start":1434212775,"timestamp_level_start":1434213144},"37650":{"id":37650,"level":68,"players":999,"active_players":462,"clicks":"1476878","abilities":"260","status":2,"timestamp":1434213147,"timestamp_game_start":1434212366,"timestamp_level_start":1434213138},"37514":{"id":37514,"level":0,"players":0,"active_players":44,"clicks":null,"abilities":null,"status":3,"timestamp":1434211282,"timestamp_game_start":1434211282,"timestamp_level_start":1434211282},"37549":{"id":37549,"level":0,"players":0,"active_players":0,"clicks":null,"abilities":null,"status":3,"timestamp":1434211614,"timestamp_game_start":1434211289,"timestamp_level_start":1434211289},"37561":{"id":37561,"level":220,"players":1500,"active_players":943,"clicks":"4813674","abilities":"1686","status":2,"timestamp":1434213147,"timestamp_game_start":1434211820,"timestamp_level_start":1434213143},"37616":{"id":37616,"level":96,"players":1003,"active_players":493,"clicks":"2161341","abilities":"492","status":2,"timestamp":1434213147,"timestamp_game_start":1434212116,"timestamp_level_start":1434213147},"37625":{"id":37625,"level":70,"players":1039,"active_players":541,"clicks":"1585612","abilities":"279","status":2,"timestamp":1434213147,"timestamp_game_start":1434212391,"timestamp_level_start":1434213143},"37637":{"id":37637,"level":69,"players":1006,"active_players":524,"clicks":"1584523","abilities":"293","status":2,"timestamp":1434213147,"timestamp_game_start":1434212372,"timestamp_level_start":1434213136},"37509":{"id":37509,"level":0,"players":0,"active_players":45,"clicks":null,"abilities":null,"status":3,"timestamp":1434211255,"timestamp_game_start":1434211255,"timestamp_level_start":1434211255},"37539":{"id":37539,"level":0,"players":0,"active_players":132,"clicks":null,"abilities":null,"status":3,"timestamp":1434211300,"timestamp_game_start":1434211300,"timestamp_level_start":1434211300},"37605":{"id":37605,"level":103,"players":1012,"active_players":518,"clicks":"2275323","abilities":"480","status":2,"timestamp":1434213147,"timestamp_game_start":1434212090,"timestamp_level_start":1434213133},"37575":{"id":37575,"level":159,"players":1205,"active_players":659,"clicks":"4122625","abilities":"1036","status":2,"timestamp":1434213147,"timestamp_game_start":1434211827,"timestamp_level_start":1434213139},"37665":{"id":37665,"level":33,"players":1005,"active_players":604,"clicks":"635043","abilities":"84","status":2,"timestamp":1434213147,"timestamp_game_start":1434212751,"timestamp_level_start":1434213145},"37684":{"id":37684,"level":21,"players":993,"active_players":587,"clicks":"528249","abilities":"40","status":2,"timestamp":1434213147,"timestamp_game_start":1434212858,"timestamp_level_start":1434213147},"37508":{"id":37508,"level":23,"players":791,"active_players":408,"clicks":"631435","abilities":"58","status":3,"timestamp":1434211201,"timestamp_game_start":1434210691,"timestamp_level_start":1434211196},"37571":{"id":37571,"level":104,"players":1023,"active_players":526,"clicks":"2389177","abilities":"428","status":2,"timestamp":1434213147,"timestamp_game_start":1434212133,"timestamp_level_start":1434213143},"37703":{"id":37703,"level":1,"players":996,"active_players":371,"clicks":"41745","abilities":"1","status":2,"timestamp":1434213147,"timestamp_game_start":1434213098,"timestamp_level_start":1434213135},"37504":{"id":37504,"level":0,"players":0,"active_players":47,"clicks":null,"abilities":null,"status":3,"timestamp":1434211222,"timestamp_game_start":1434211222,"timestamp_level_start":1434211222},"37596":{"id":37596,"level":107,"players":1033,"active_players":524,"clicks":"2369130","abilities":"627","status":2,"timestamp":1434213147,"timestamp_game_start":1434212065,"timestamp_level_start":1434213142},"37612":{"id":37612,"level":95,"players":1014,"active_players":497,"clicks":"2311312","abilities":"404","status":2,"timestamp":1434213147,"timestamp_game_start":1434212115,"timestamp_level_start":1434213143},"37515":{"id":37515,"level":31,"players":807,"active_players":371,"clicks":"827955","abilities":"88","status":3,"timestamp":1434211201,"timestamp_game_start":1434210528,"timestamp_level_start":1434211199},"37594":{"id":37594,"level":104,"players":1018,"active_players":478,"clicks":"2389296","abilities":"501","status":2,"timestamp":1434213147,"timestamp_game_start":1434212052,"timestamp_level_start":1434213138},"37647":{"id":37647,"level":68,"players":1014,"active_players":507,"clicks":"1457022","abilities":"270","status":2,"timestamp":1434213147,"timestamp_game_start":1434212396,"timestamp_level_start":1434213145},"37589":{"id":37589,"level":108,"players":1084,"active_players":552,"clicks":"2720477","abilities":"502","status":2,"timestamp":1434213147,"timestamp_game_start":1434212073,"timestamp_level_start":1434213144},"37643":{"id":37643,"level":60,"players":998,"active_players":506,"clicks":"1328648","abilities":"218","status":2,"timestamp":1434213147,"timestamp_game_start":1434212466,"timestamp_level_start":1434213142},"37543":{"id":37543,"level":0,"players":0,"active_players":57,"clicks":null,"abilities":null,"status":3,"timestamp":1434211250,"timestamp_game_start":1434211250,"timestamp_level_start":1434211250},"37664":{"id":37664,"level":26,"players":986,"active_players":549,"clicks":"570432","abilities":"48","status":2,"timestamp":1434213147,"timestamp_game_start":1434212782,"timestamp_level_start":1434213147},"37553":{"id":37553,"level":153,"players":1186,"active_players":627,"clicks":"3293252","abilities":"896","status":2,"timestamp":1434213147,"timestamp_game_start":1434211813,"timestamp_level_start":1434213145},"37657":{"id":37657,"level":68,"players":990,"active_players":506,"clicks":"1456090","abilities":"271","status":2,"timestamp":1434213147,"timestamp_game_start":1434212402,"timestamp_level_start":1434213146},"37542":{"id":37542,"level":0,"players":0,"active_players":46,"clicks":null,"abilities":null,"status":3,"timestamp":1434211224,"timestamp_game_start":1434211224,"timestamp_level_start":1434211224},"37620":{"id":37620,"level":100,"players":1042,"active_players":499,"clicks":"2572042","abilities":"461","status":2,"timestamp":1434213147,"timestamp_game_start":1434212117,"timestamp_level_start":1434213133},"37645":{"id":37645,"level":109,"players":1500,"active_players":962,"clicks":"2507399","abilities":"753","status":2,"timestamp":1434213147,"timestamp_game_start":1434212392,"timestamp_level_start":1434213146},"37584":{"id":37584,"level":221,"players":1500,"active_players":938,"clicks":"186607668080","abilities":"1606","status":2,"timestamp":1434213147,"timestamp_game_start":1434211844,"timestamp_level_start":1434213144},"37627":{"id":37627,"level":66,"players":1015,"active_players":536,"clicks":"1453561","abilities":"251","status":2,"timestamp":1434213147,"timestamp_game_start":1434212430,"timestamp_level_start":1434213138},"37668":{"id":37668,"level":33,"players":1001,"active_players":559,"clicks":"758632","abilities":"79","status":2,"timestamp":1434213147,"timestamp_game_start":1434212733,"timestamp_level_start":1434213143},"37640":{"id":37640,"level":64,"players":996,"active_players":496,"clicks":"1205677","abilities":"239","status":2,"timestamp":1434213147,"timestamp_game_start":1434212429,"timestamp_level_start":1434213137},"37634":{"id":37634,"level":69,"players":1006,"active_players":502,"clicks":"1624205","abilities":"272","status":2,"timestamp":1434213147,"timestamp_game_start":1434212390,"timestamp_level_start":1434213144},"37512":{"id":37512,"level":34,"players":820,"active_players":392,"clicks":"921674","abilities":"117","status":3,"timestamp":1434211201,"timestamp_game_start":1434210476,"timestamp_level_start":1434211190},"37617":{"id":37617,"level":100,"players":1050,"active_players":551,"clicks":"2385878","abilities":"495","status":2,"timestamp":1434213147,"timestamp_game_start":1434212106,"timestamp_level_start":1434213141},"37655":{"id":37655,"level":73,"players":999,"active_players":524,"clicks":"1609200","abilities":"299","status":2,"timestamp":1434213147,"timestamp_game_start":1434212378,"timestamp_level_start":1434213142},"37723":{"id":37723,"level":5,"players":1001,"active_players":567,"clicks":"158377","abilities":"3","status":2,"timestamp":1434213147,"timestamp_game_start":1434213027,"timestamp_level_start":1434213131},"37521":{"id":37521,"level":0,"players":1,"active_players":165,"clicks":null,"abilities":null,"status":3,"timestamp":1434211302,"timestamp_game_start":1434211302,"timestamp_level_start":1434211302},"37624":{"id":37624,"level":67,"players":992,"active_players":522,"clicks":"1424990","abilities":"257","status":2,"timestamp":1434213147,"timestamp_game_start":1434212412,"timestamp_level_start":1434213139},"37693":{"id":37693,"level":24,"players":1001,"active_players":557,"clicks":"844568","abilities":"54","status":2,"timestamp":1434213147,"timestamp_game_start":1434212793,"timestamp_level_start":1434213142},"37513":{"id":37513,"level":0,"players":0,"active_players":47,"clicks":null,"abilities":null,"status":3,"timestamp":1434211228,"timestamp_game_start":1434211228,"timestamp_level_start":1434211228},"37659":{"id":37659,"level":64,"players":1010,"active_players":530,"clicks":"1245478","abilities":"223","status":2,"timestamp":1434213147,"timestamp_game_start":1434212423,"timestamp_level_start":1434213144},"37678":{"id":37678,"level":19,"players":991,"active_players":561,"clicks":"3200456456","abilities":"29","status":2,"timestamp":1434213147,"timestamp_game_start":1434212859,"timestamp_level_start":1434213138},"37629":{"id":37629,"level":67,"players":1009,"active_players":496,"clicks":"1386208","abilities":"252","status":2,"timestamp":1434213147,"timestamp_game_start":1434212367,"timestamp_level_start":1434213143},"37646":{"id":37646,"level":78,"players":1011,"active_players":553,"clicks":"1799796","abilities":"328","status":2,"timestamp":1434213147,"timestamp_game_start":1434212399,"timestamp_level_start":1434213146},"37671":{"id":37671,"level":26,"players":1201,"active_players":694,"clicks":"675627","abilities":"61","status":2,"timestamp":1434213147,"timestamp_game_start":1434212795,"timestamp_level_start":1434213145},"37621":{"id":37621,"level":126,"players":1031,"active_players":518,"clicks":"6274968","abilities":"530","status":2,"timestamp":1434213147,"timestamp_game_start":1434212064,"timestamp_level_start":1434213146},"37503":{"id":37503,"level":0,"players":0,"active_players":46,"clicks":null,"abilities":null,"status":3,"timestamp":1434211234,"timestamp_game_start":1434211234,"timestamp_level_start":1434211234},"37651":{"id":37651,"level":124,"players":1500,"active_players":1063,"clicks":"365938653158","abilities":"1035","status":2,"timestamp":1434213147,"timestamp_game_start":1434212252,"timestamp_level_start":1434213147},"37653":{"id":37653,"level":64,"players":1014,"active_players":558,"clicks":"1337863","abilities":"220","status":2,"timestamp":1434213147,"timestamp_game_start":1434212454,"timestamp_level_start":1434213146},"37577":{"id":37577,"level":91,"players":1033,"active_players":486,"clicks":"2140630","abilities":"455","status":2,"timestamp":1434213147,"timestamp_game_start":1434212101,"timestamp_level_start":1434213139},"37622":{"id":37622,"level":99,"players":1031,"active_players":515,"clicks":"2274856","abilities":"512","status":2,"timestamp":1434213147,"timestamp_game_start":1434212089,"timestamp_level_start":1434213138},"37574":{"id":37574,"level":157,"players":1131,"active_players":609,"clicks":"3512270","abilities":"964","status":2,"timestamp":1434213147,"timestamp_game_start":1434211827,"timestamp_level_start":1434213147},"37642":{"id":37642,"level":57,"players":1017,"active_players":500,"clicks":"1281628","abilities":"215","status":2,"timestamp":1434213147,"timestamp_game_start":1434212452,"timestamp_level_start":1434213146},"37658":{"id":37658,"level":69,"players":998,"active_players":537,"clicks":"1375204","abilities":"264","status":2,"timestamp":1434213147,"timestamp_game_start":1434212426,"timestamp_level_start":1434213137},"37660":{"id":37660,"level":24,"players":995,"active_players":574,"clicks":"599513","abilities":"46","status":2,"timestamp":1434213147,"timestamp_game_start":1434212787,"timestamp_level_start":1434213142},"37652":{"id":37652,"level":63,"players":995,"active_players":498,"clicks":"1404782","abilities":"181","status":2,"timestamp":1434213147,"timestamp_game_start":1434212449,"timestamp_level_start":1434213144},"37580":{"id":37580,"level":150,"players":1137,"active_players":591,"clicks":"4037955","abilities":"942","status":2,"timestamp":1434213147,"timestamp_game_start":1434211837,"timestamp_level_start":1434213147},"37613":{"id":37613,"level":119,"players":1031,"active_players":539,"clicks":"3032177","abilities":"582","status":2,"timestamp":1434213147,"timestamp_game_start":1434212042,"timestamp_level_start":1434213135},"37565":{"id":37565,"level":159,"players":1156,"active_players":643,"clicks":"3605196","abilities":"1087","status":2,"timestamp":1434213147,"timestamp_game_start":1434211825,"timestamp_level_start":1434213126},"37505":{"id":37505,"level":0,"players":0,"active_players":36,"clicks":null,"abilities":null,"status":3,"timestamp":1434211244,"timestamp_game_start":1434211244,"timestamp_level_start":1434211244},"37632":{"id":37632,"level":74,"players":1001,"active_players":511,"clicks":"1506578","abilities":"337","status":2,"timestamp":1434213147,"timestamp_game_start":1434212366,"timestamp_level_start":1434213139},"37641":{"id":37641,"level":65,"players":1019,"active_players":505,"clicks":"1530566","abilities":"231","status":2,"timestamp":1434213147,"timestamp_game_start":1434212404,"timestamp_level_start":1434213145},"37601":{"id":37601,"level":134,"players":1039,"active_players":532,"clicks":"4690448","abilities":"589","status":2,"timestamp":1434213147,"timestamp_game_start":1434212066,"timestamp_level_start":1434213145},"37619":{"id":37619,"level":97,"players":1031,"active_players":504,"clicks":"2040078","abilities":"430","status":2,"timestamp":1434213147,"timestamp_game_start":1434212076,"timestamp_level_start":1434213141},"37607":{"id":37607,"level":116,"players":1043,"active_players":532,"clicks":"3046910","abilities":"614","status":2,"timestamp":1434213147,"timestamp_game_start":1434212027,"timestamp_level_start":1434213146},"37526":{"id":37526,"level":0,"players":0,"active_players":0,"clicks":null,"abilities":null,"status":3,"timestamp":1434211616,"timestamp_game_start":1434211245,"timestamp_level_start":1434211245},"37610":{"id":37610,"level":100,"players":1033,"active_players":511,"clicks":"2133469","abilities":"494","status":2,"timestamp":1434213147,"timestamp_game_start":1434212086,"timestamp_level_start":1434213144},"37676":{"id":37676,"level":29,"players":988,"active_players":557,"clicks":"621922","abilities":"70","status":2,"timestamp":1434213147,"timestamp_game_start":1434212791,"timestamp_level_start":1434213140},"37563":{"id":37563,"level":150,"players":1230,"active_players":648,"clicks":"3621264","abilities":"931","status":2,"timestamp":1434213147,"timestamp_game_start":1434211834,"timestamp_level_start":1434213145},"37595":{"id":37595,"level":102,"players":1009,"active_players":473,"clicks":"2261015","abilities":"488","status":2,"timestamp":1434213147,"timestamp_game_start":1434212000,"timestamp_level_start":1434213144},"37670":{"id":37670,"level":28,"players":1008,"active_players":579,"clicks":"692335","abilities":"56","status":2,"timestamp":1434213147,"timestamp_game_start":1434212763,"timestamp_level_start":1434213138},"37609":{"id":37609,"level":114,"players":1044,"active_players":538,"clicks":"2645835","abilities":"550","status":2,"timestamp":1434213147,"timestamp_game_start":1434212089,"timestamp_level_start":1434213146},"37674":{"id":37674,"level":20,"players":995,"active_players":570,"clicks":"605533","abilities":"41","status":2,"timestamp":1434213147,"timestamp_game_start":1434212850,"timestamp_level_start":1434213144},"37559":{"id":37559,"level":370,"players":1500,"active_players":1129,"clicks":"24769852889","abilities":"3344","status":2,"timestamp":1434213147,"timestamp_game_start":1434211782,"timestamp_level_start":1434213146},"37593":{"id":37593,"level":117,"players":1054,"active_players":499,"clicks":"3347790","abilities":"532","status":2,"timestamp":1434213147,"timestamp_game_start":1434212049,"timestamp_level_start":1434213143},"37690":{"id":37690,"level":28,"players":1005,"active_players":580,"clicks":"675426","abilities":"62","status":2,"timestamp":1434213147,"timestamp_game_start":1434212786,"timestamp_level_start":1434213143},"37564":{"id":37564,"level":109,"players":1017,"active_players":540,"clicks":"2613658","abilities":"539","status":2,"timestamp":1434213147,"timestamp_game_start":1434212116,"timestamp_level_start":1434213134},"37568":{"id":37568,"level":158,"players":1117,"active_players":613,"clicks":"3721675","abilities":"943","status":2,"timestamp":1434213147,"timestamp_game_start":1434211837,"timestamp_level_start":1434213145},"37631":{"id":37631,"level":81,"players":1009,"active_players":506,"clicks":"1874113","abilities":"328","status":2,"timestamp":1434213147,"timestamp_game_start":1434212302,"timestamp_level_start":1434213142},"37661":{"id":37661,"level":28,"players":998,"active_players":576,"clicks":"700892","abilities":"59","status":2,"timestamp":1434213147,"timestamp_game_start":1434212789,"timestamp_level_start":1434213140},"37648":{"id":37648,"level":64,"players":991,"active_players":519,"clicks":"1404744","abilities":"256","status":2,"timestamp":1434213147,"timestamp_game_start":1434212465,"timestamp_level_start":1434213141},"37644":{"id":37644,"level":65,"players":989,"active_players":506,"clicks":"1351899","abilities":"234","status":2,"timestamp":1434213147,"timestamp_game_start":1434212416,"timestamp_level_start":1434213141},"37579":{"id":37579,"level":141,"players":1083,"active_players":610,"clicks":"3477900","abilities":"829","status":2,"timestamp":1434213147,"timestamp_game_start":1434211852,"timestamp_level_start":1434213141},"37626":{"id":37626,"level":65,"players":1006,"active_players":545,"clicks":"1228782","abilities":"239","status":2,"timestamp":1434213147,"timestamp_game_start":1434212436,"timestamp_level_start":1434213143},"37602":{"id":37602,"level":129,"players":1062,"active_players":555,"clicks":"3756163","abilities":"711","status":2,"timestamp":1434213147,"timestamp_game_start":1434211982,"timestamp_level_start":1434213147},"37510":{"id":37510,"level":0,"players":0,"active_players":39,"clicks":null,"abilities":null,"status":3,"timestamp":1434211231,"timestamp_game_start":1434211231,"timestamp_level_start":1434211231},"37688":{"id":37688,"level":21,"players":1003,"active_players":624,"clicks":"617655","abilities":"45","status":2,"timestamp":1434213147,"timestamp_game_start":1434212851,"timestamp_level_start":1434213143},"37576":{"id":37576,"level":147,"players":1166,"active_players":629,"clicks":"3652227","abilities":"892","status":2,"timestamp":1434213147,"timestamp_game_start":1434211848,"timestamp_level_start":1434213146},"37522":{"id":37522,"level":0,"players":1,"active_players":55,"clicks":null,"abilities":null,"status":3,"timestamp":1434211227,"timestamp_game_start":1434211227,"timestamp_level_start":1434211227},"37623":{"id":37623,"level":105,"players":1032,"active_players":534,"clicks":"2503617","abilities":"518","status":2,"timestamp":1434213147,"timestamp_game_start":1434212107,"timestamp_level_start":1434213141},"37569":{"id":37569,"level":175,"players":1427,"active_players":820,"clicks":"4392429","abilities":"1141","status":2,"timestamp":1434213147,"timestamp_game_start":1434211837,"timestamp_level_start":1434213145},"37667":{"id":37667,"level":38,"players":975,"active_players":571,"clicks":"881924","abilities":"106","status":2,"timestamp":1434213147,"timestamp_game_start":1434212689,"timestamp_level_start":1434213141},"37618":{"id":37618,"level":103,"players":1010,"active_players":523,"clicks":"2542691","abilities":"461","status":2,"timestamp":1434213147,"timestamp_game_start":1434212092,"timestamp_level_start":1434213144},"37636":{"id":37636,"level":65,"players":1007,"active_players":553,"clicks":"1400033","abilities":"261","status":2,"timestamp":1434213147,"timestamp_game_start":1434212448,"timestamp_level_start":1434213145},"37570":{"id":37570,"level":103,"players":1029,"active_players":534,"clicks":"406947620","abilities":"483","status":2,"timestamp":1434213147,"timestamp_game_start":1434212119,"timestamp_level_start":1434213142},"37677":{"id":37677,"level":25,"players":1003,"active_players":564,"clicks":"639433","abilities":"55","status":2,"timestamp":1434213148,"timestamp_game_start":1434212783,"timestamp_level_start":1434213146},"37582":{"id":37582,"level":140,"players":1103,"active_players":580,"clicks":"3555684","abilities":"793","status":2,"timestamp":1434213148,"timestamp_game_start":1434211832,"timestamp_level_start":1434213139},"37638":{"id":37638,"level":69,"players":1005,"active_players":552,"clicks":"1531777","abilities":"268","status":2,"timestamp":1434213148,"timestamp_game_start":1434212441,"timestamp_level_start":1434213141},"37598":{"id":37598,"level":109,"players":1057,"active_players":531,"clicks":"2482985","abilities":"553","status":2,"timestamp":1434213148,"timestamp_game_start":1434212071,"timestamp_level_start":1434213135},"37562":{"id":37562,"level":161,"players":1214,"active_players":666,"clicks":"3583919","abilities":"1006","status":2,"timestamp":1434213148,"timestamp_game_start":1434211817,"timestamp_level_start":1434213144},"37547":{"id":37547,"level":0,"players":0,"active_players":216,"clicks":null,"abilities":null,"status":3,"timestamp":1434211276,"timestamp_game_start":1434211276,"timestamp_level_start":1434211276},"37608":{"id":37608,"level":109,"players":1041,"active_players":545,"clicks":"2552941","abilities":"465","status":2,"timestamp":1434213148,"timestamp_game_start":1434212105,"timestamp_level_start":1434213142},"37585":{"id":37585,"level":134,"players":1072,"active_players":545,"clicks":"3322674","abilities":"691","status":2,"timestamp":1434213148,"timestamp_game_start":1434211833,"timestamp_level_start":1434213147},"37695":{"id":37695,"level":26,"players":1008,"active_players":589,"clicks":"722018","abilities":"58","status":2,"timestamp":1434213148,"timestamp_game_start":1434212793,"timestamp_level_start":1434213141},"37531":{"id":37531,"level":0,"players":0,"active_players":40,"clicks":null,"abilities":null,"status":3,"timestamp":1434211253,"timestamp_game_start":1434211253,"timestamp_level_start":1434211253},"37524":{"id":37524,"level":0,"players":0,"active_players":236,"clicks":null,"abilities":null,"status":3,"timestamp":1434211264,"timestamp_game_start":1434211264,"timestamp_level_start":1434211264},"37583":{"id":37583,"level":156,"players":1106,"active_players":605,"clicks":"3505159","abilities":"898","status":2,"timestamp":1434213148,"timestamp_game_start":1434211830,"timestamp_level_start":1434213145},"37669":{"id":37669,"level":23,"players":994,"active_players":577,"clicks":"550308","abilities":"39","status":2,"timestamp":1434213148,"timestamp_game_start":1434212796,"timestamp_level_start":1434213142},"37666":{"id":37666,"level":31,"players":1002,"active_players":570,"clicks":"676219","abilities":"69","status":2,"timestamp":1434213148,"timestamp_game_start":1434212723,"timestamp_level_start":1434213141},"37691":{"id":37691,"level":34,"players":1000,"active_players":577,"clicks":"742342","abilities":"88","status":2,"timestamp":1434213148,"timestamp_game_start":1434212724,"timestamp_level_start":1434213141},"37663":{"id":37663,"level":20,"players":1007,"active_players":579,"clicks":"571962","abilities":"32","status":2,"timestamp":1434213148,"timestamp_game_start":1434212836,"timestamp_level_start":1434213141},"37604":{"id":37604,"level":98,"players":1015,"active_players":501,"clicks":"2259245","abilities":"441","status":2,"timestamp":1434213148,"timestamp_game_start":1434212103,"timestamp_level_start":1434213140},"37567":{"id":37567,"level":156,"players":1224,"active_players":679,"clicks":"4276854","abilities":"979","status":2,"timestamp":1434213148,"timestamp_game_start":1434211818,"timestamp_level_start":1434213147},"37560":{"id":37560,"level":172,"players":1156,"active_players":665,"clicks":"4373293","abilities":"1076","status":2,"timestamp":1434213148,"timestamp_game_start":1434211817,"timestamp_level_start":1434213144},"37614":{"id":37614,"level":100,"players":1060,"active_players":514,"clicks":"2625070","abilities":"482","status":2,"timestamp":1434213148,"timestamp_game_start":1434212047,"timestamp_level_start":1434213138},"37694":{"id":37694,"level":24,"players":989,"active_players":588,"clicks":"653910","abilities":"42","status":2,"timestamp":1434213148,"timestamp_game_start":1434212810,"timestamp_level_start":1434213141},"37516":{"id":37516,"level":9,"players":787,"active_players":413,"clicks":"568233","abilities":"25","status":3,"timestamp":1434211201,"timestamp_game_start":1434210815,"timestamp_level_start":1434211098},"37662":{"id":37662,"level":20,"players":990,"active_players":584,"clicks":"539211","abilities":"39","status":2,"timestamp":1434213148,"timestamp_game_start":1434212847,"timestamp_level_start":1434213148},"37525":{"id":37525,"level":0,"players":0,"active_players":119,"clicks":null,"abilities":null,"status":3,"timestamp":1434211301,"timestamp_game_start":1434211301,"timestamp_level_start":1434211301},"37630":{"id":37630,"level":66,"players":1021,"active_players":519,"clicks":"1332330","abilities":"247","status":2,"timestamp":1434213148,"timestamp_game_start":1434212363,"timestamp_level_start":1434213144},"37675":{"id":37675,"level":24,"players":1007,"active_players":576,"clicks":"720944","abilities":"44","status":2,"timestamp":1434213148,"timestamp_game_start":1434212778,"timestamp_level_start":1434213144},"37587":{"id":37587,"level":154,"players":1127,"active_players":589,"clicks":"4247557","abilities":"843","status":2,"timestamp":1434213149,"timestamp_game_start":1434211845,"timestamp_level_start":1434213145},"37615":{"id":37615,"level":98,"players":1078,"active_players":572,"clicks":"2639835","abilities":"442","status":2,"timestamp":1434213149,"timestamp_game_start":1434212114,"timestamp_level_start":1434213144},"37572":{"id":37572,"level":158,"players":1166,"active_players":597,"clicks":"3674374","abilities":"1040","status":2,"timestamp":1434213149,"timestamp_game_start":1434211841,"timestamp_level_start":1434213148},"37679":{"id":37679,"level":18,"players":991,"active_players":570,"clicks":"472701","abilities":"24","status":2,"timestamp":1434213149,"timestamp_game_start":1434212876,"timestamp_level_start":1434213144},"37588":{"id":37588,"level":111,"players":1018,"active_players":520,"clicks":"2466928","abilities":"579","status":2,"timestamp":1434213149,"timestamp_game_start":1434212074,"timestamp_level_start":1434213140},"37689":{"id":37689,"level":19,"players":1000,"active_players":591,"clicks":"448328","abilities":"33","status":2,"timestamp":1434213149,"timestamp_game_start":1434212870,"timestamp_level_start":1434213148},"37556":{"id":37556,"level":170,"players":1260,"active_players":712,"clicks":"4110228","abilities":"1071","status":2,"timestamp":1434213149,"timestamp_game_start":1434211822,"timestamp_level_start":1434213145},"37649":{"id":37649,"level":76,"players":1021,"active_players":557,"clicks":"1560802","abilities":"289","status":2,"timestamp":1434213149,"timestamp_game_start":1434212432,"timestamp_level_start":1434213147},"37682":{"id":37682,"level":29,"players":998,"active_players":578,"clicks":"611281","abilities":"47","status":2,"timestamp":1434213149,"timestamp_game_start":1434212793,"timestamp_level_start":1434213144},"37573":{"id":37573,"level":161,"players":1086,"active_players":582,"clicks":"3964636","abilities":"940","status":2,"timestamp":1434213149,"timestamp_game_start":1434211842,"timestamp_level_start":1434213149},"37557":{"id":37557,"level":165,"players":1107,"active_players":614,"clicks":"4397754","abilities":"986","status":2,"timestamp":1434213149,"timestamp_game_start":1434211820,"timestamp_level_start":1434213145},"37635":{"id":37635,"level":58,"players":987,"active_players":511,"clicks":"1202815","abilities":"221","status":2,"timestamp":1434213149,"timestamp_game_start":1434212416,"timestamp_level_start":1434213145},"37507":{"id":37507,"level":38,"players":835,"active_players":322,"clicks":"996792","abilities":"122","status":3,"timestamp":1434211201,"timestamp_game_start":1434210359,"timestamp_level_start":1434211200},"37654":{"id":37654,"level":70,"players":1011,"active_players":525,"clicks":"1348592","abilities":"280","status":2,"timestamp":1434213149,"timestamp_game_start":1434212397,"timestamp_level_start":1434213148},"37511":{"id":37511,"level":4,"players":0,"active_players":418,"clicks":"145193","abilities":"1","status":3,"timestamp":1434211201,"timestamp_game_start":1434211076,"timestamp_level_start":1434211193},"37687":{"id":37687,"level":48,"players":1030,"active_players":562,"clicks":"1024568","abilities":"122","status":2,"timestamp":1434213148,"timestamp_game_start":1434212617,"timestamp_level_start":1434213144},"37681":{"id":37681,"level":32,"players":989,"active_players":584,"clicks":"6355420","abilities":"70","status":2,"timestamp":1434213148,"timestamp_game_start":1434212761,"timestamp_level_start":1434213148},"37590":{"id":37590,"level":111,"players":1017,"active_players":546,"clicks":"2715450","abilities":"500","status":2,"timestamp":1434213149,"timestamp_game_start":1434212099,"timestamp_level_start":1434213145},"37548":{"id":37548,"level":0,"players":0,"active_players":41,"clicks":null,"abilities":null,"status":3,"timestamp":1434211294,"timestamp_game_start":1434211294,"timestamp_level_start":1434211294},"37628":{"id":37628,"level":63,"players":1132,"active_players":487,"clicks":"1233927","abilities":"246","status":2,"timestamp":1434213149,"timestamp_game_start":1434212396,"timestamp_level_start":1434213139},"37506":{"id":37506,"level":74,"players":0,"active_players":271,"clicks":"1746958","abilities":"373","status":3,"timestamp":1434211201,"timestamp_game_start":1434209685,"timestamp_level_start":1434211200},"37551":{"id":37551,"level":0,"players":610,"active_players":44,"clicks":null,"abilities":null,"status":3,"timestamp":1434211267,"timestamp_game_start":1434211267,"timestamp_level_start":1434211267}}