{"37557":{"id":37557,"level":413,"players":1276,"active_players":466,"clicks":"11063720","abilities":"3063","status":2,"timestamp":1434215279,"timestamp_game_start":1434211820,"timestamp_level_start":1434215277},"37507":{"id":37507,"level":38,"players":766,"active_players":322,"clicks":"996792","abilities":"122","status":3,"timestamp":1434211201,"timestamp_game_start":1434210359,"timestamp_level_start":1434211200},"37542":{"id":37542,"level":0,"players":0,"active_players":46,"clicks":null,"abilities":null,"status":3,"timestamp":1434211224,"timestamp_game_start":1434211224,"timestamp_level_start":1434211224},"37566":{"id":37566,"level":321,"players":1176,"active_players":362,"clicks":"6924289","abilities":"2168","status":2,"timestamp":1434215279,"timestamp_game_start":1434212120,"timestamp_level_start":1434215277},"37514":{"id":37514,"level":0,"players":0,"active_players":44,"clicks":null,"abilities":null,"status":3,"timestamp":1434211282,"timestamp_game_start":1434211282,"timestamp_level_start":1434211282},"37577":{"id":37577,"level":249,"players":1096,"active_players":295,"clicks":"5719960","abilities":"1640","status":2,"timestamp":1434215279,"timestamp_game_start":1434212101,"timestamp_level_start":1434215276},"37504":{"id":37504,"level":0,"players":0,"active_players":47,"clicks":null,"abilities":null,"status":3,"timestamp":1434211222,"timestamp_game_start":1434211222,"timestamp_level_start":1434211222},"37581":{"id":37581,"level":412,"players":1500,"active_players":490,"clicks":"10534455","abilities":"3090","status":2,"timestamp":1434215279,"timestamp_game_start":1434211844,"timestamp_level_start":1434215275},"37714":{"id":37714,"level":148,"players":1004,"active_players":243,"clicks":"2998317","abilities":"721","status":2,"timestamp":1434215279,"timestamp_game_start":1434213306,"timestamp_level_start":1434215277},"37571":{"id":37571,"level":284,"players":1067,"active_players":351,"clicks":"6665072","abilities":"1803","status":2,"timestamp":1434215279,"timestamp_game_start":1434212133,"timestamp_level_start":1434215277},"37579":{"id":37579,"level":367,"players":1165,"active_players":409,"clicks":"8310159","abilities":"2617","status":2,"timestamp":1434215279,"timestamp_game_start":1434211852,"timestamp_level_start":1434215276},"37711":{"id":37711,"level":131,"players":1030,"active_players":239,"clicks":"3000260","abilities":"708","status":2,"timestamp":1434215279,"timestamp_game_start":1434213193,"timestamp_level_start":1434215275},"37717":{"id":37717,"level":149,"players":1025,"active_players":252,"clicks":"3202579","abilities":"755","status":2,"timestamp":1434215279,"timestamp_game_start":1434213199,"timestamp_level_start":1434215240},"37751":{"id":37751,"level":98,"players":1015,"active_players":269,"clicks":"1875066","abilities":"469","status":2,"timestamp":1434215279,"timestamp_game_start":1434213829,"timestamp_level_start":1434215278},"37574":{"id":37574,"level":396,"players":1399,"active_players":520,"clicks":"8952170","abilities":"3037","status":2,"timestamp":1434215279,"timestamp_game_start":1434211827,"timestamp_level_start":1434215273},"37778":{"id":37778,"level":85,"players":1026,"active_players":322,"clicks":"1775750","abilities":"388","status":2,"timestamp":1434215279,"timestamp_game_start":1434214077,"timestamp_level_start":1434215269},"37803":{"id":37803,"level":84,"players":997,"active_players":350,"clicks":"1919850","abilities":"343","status":2,"timestamp":1434215279,"timestamp_game_start":1434214220,"timestamp_level_start":1434215275},"37680":{"id":37680,"level":150,"players":1043,"active_players":219,"clicks":"3205554","abilities":"818","status":2,"timestamp":1434215279,"timestamp_game_start":1434212811,"timestamp_level_start":1434215269},"37597":{"id":37597,"level":298,"players":1137,"active_players":344,"clicks":"5991931","abilities":"1911","status":2,"timestamp":1434215279,"timestamp_game_start":1434212072,"timestamp_level_start":1434215270},"37587":{"id":37587,"level":366,"players":1245,"active_players":456,"clicks":"10450718","abilities":"2625","status":2,"timestamp":1434215279,"timestamp_game_start":1434211845,"timestamp_level_start":1434215273},"37740":{"id":37740,"level":109,"players":1005,"active_players":250,"clicks":"2124944","abilities":"512","status":2,"timestamp":1434215279,"timestamp_game_start":1434213643,"timestamp_level_start":1434215270},"37656":{"id":37656,"level":200,"players":1050,"active_players":247,"clicks":"4376106","abilities":"1214","status":2,"timestamp":1434215279,"timestamp_game_start":1434212453,"timestamp_level_start":1434215275},"37716":{"id":37716,"level":133,"players":1021,"active_players":237,"clicks":"2799787","abilities":"733","status":2,"timestamp":1434215279,"timestamp_game_start":1434213244,"timestamp_level_start":1434215266},"37624":{"id":37624,"level":233,"players":1047,"active_players":267,"clicks":"4664401","abilities":"1398","status":2,"timestamp":1434215279,"timestamp_game_start":1434212412,"timestamp_level_start":1434215277},"37826":{"id":37826,"level":42,"players":1010,"active_players":434,"clicks":"931527","abilities":"134","status":2,"timestamp":1434215279,"timestamp_game_start":1434214671,"timestamp_level_start":1434215276},"37561":{"id":37561,"level":580,"players":1500,"active_players":615,"clicks":"25321907","abilities":"4792","status":2,"timestamp":1434215279,"timestamp_game_start":1434211820,"timestamp_level_start":1434215273},"37703":{"id":37703,"level":149,"players":1009,"active_players":236,"clicks":"3142751","abilities":"833","status":2,"timestamp":1434215279,"timestamp_game_start":1434213098,"timestamp_level_start":1434215233},"37646":{"id":37646,"level":281,"players":1086,"active_players":322,"clicks":"6656494","abilities":"1804","status":2,"timestamp":1434215279,"timestamp_game_start":1434212399,"timestamp_level_start":1434215271},"37661":{"id":37661,"level":189,"players":1028,"active_players":254,"clicks":"3942548","abilities":"1044","status":2,"timestamp":1434215279,"timestamp_game_start":1434212789,"timestamp_level_start":1434215218},"37747":{"id":37747,"level":115,"players":1027,"active_players":272,"clicks":"2574918","abilities":"584","status":2,"timestamp":1434215279,"timestamp_game_start":1434213646,"timestamp_level_start":1434215263},"37806":{"id":37806,"level":30,"players":1004,"active_players":473,"clicks":"736994","abilities":"87","status":2,"timestamp":1434215279,"timestamp_game_start":1434214802,"timestamp_level_start":1434215274},"37517":{"id":37517,"level":0,"players":0,"active_players":58,"clicks":null,"abilities":null,"status":3,"timestamp":1434211218,"timestamp_game_start":1434211218,"timestamp_level_start":1434211218},"37589":{"id":37589,"level":298,"players":1170,"active_players":338,"clicks":"7213471","abilities":"1849","status":2,"timestamp":1434215279,"timestamp_game_start":1434212073,"timestamp_level_start":1434215270},"37556":{"id":37556,"level":496,"players":1500,"active_players":593,"clicks":"11576260","abilities":"4160","status":2,"timestamp":1434215279,"timestamp_game_start":1434211822,"timestamp_level_start":1434215277},"37662":{"id":37662,"level":149,"players":1017,"active_players":220,"clicks":"3548023","abilities":"855","status":2,"timestamp":1434215279,"timestamp_game_start":1434212847,"timestamp_level_start":1434215238},"37840":{"id":37840,"level":8,"players":1000,"active_players":580,"clicks":"245949","abilities":"11","status":2,"timestamp":1434215279,"timestamp_game_start":1434215075,"timestamp_level_start":1434215264},"37572":{"id":37572,"level":400,"players":1342,"active_players":507,"clicks":"12406400","abilities":"3060","status":2,"timestamp":1434215279,"timestamp_game_start":1434211841,"timestamp_level_start":1434215270},"37852":{"id":37852,"level":1,"players":1006,"active_players":446,"clicks":"83037","abilities":null,"status":2,"timestamp":1434215279,"timestamp_game_start":1434215206,"timestamp_level_start":1434215262},"37653":{"id":37653,"level":188,"players":1050,"active_players":212,"clicks":"4223771","abilities":"1071","status":2,"timestamp":1434215279,"timestamp_game_start":1434212454,"timestamp_level_start":1434215268},"37553":{"id":37553,"level":372,"players":1377,"active_players":518,"clicks":"7876469","abilities":"2789","status":2,"timestamp":1434215279,"timestamp_game_start":1434211813,"timestamp_level_start":1434215273},"37712":{"id":37712,"level":156,"players":1032,"active_players":267,"clicks":"3176218","abilities":"874","status":2,"timestamp":1434215279,"timestamp_game_start":1434213212,"timestamp_level_start":1434215275},"37697":{"id":37697,"level":157,"players":1001,"active_players":248,"clicks":"3645811","abilities":"747","status":2,"timestamp":1434215279,"timestamp_game_start":1434213252,"timestamp_level_start":1434215271},"37658":{"id":37658,"level":229,"players":1044,"active_players":275,"clicks":"4993913","abilities":"1354","status":2,"timestamp":1434215279,"timestamp_game_start":1434212426,"timestamp_level_start":1434215256},"37853":{"id":37853,"level":7,"players":1008,"active_players":570,"clicks":"234417","abilities":"4","status":2,"timestamp":1434215279,"timestamp_game_start":1434215111,"timestamp_level_start":1434215276},"37859":{"id":37859,"level":1,"players":995,"active_players":413,"clicks":"59834","abilities":null,"status":2,"timestamp":1434215279,"timestamp_game_start":1434215209,"timestamp_level_start":1434215261},"37758":{"id":37758,"level":109,"players":1011,"active_players":290,"clicks":"2229669","abilities":"621","status":2,"timestamp":1434215279,"timestamp_game_start":1434213635,"timestamp_level_start":1434215235},"37592":{"id":37592,"level":279,"players":1037,"active_players":273,"clicks":"5795673","abilities":"1795","status":2,"timestamp":1434215279,"timestamp_game_start":1434212065,"timestamp_level_start":1434215274},"37801":{"id":37801,"level":75,"players":1022,"active_players":333,"clicks":"1740534","abilities":"305","status":2,"timestamp":1434215279,"timestamp_game_start":1434214181,"timestamp_level_start":1434215264},"37530":{"id":37530,"level":0,"players":2,"active_players":46,"clicks":null,"abilities":null,"status":3,"timestamp":1434211234,"timestamp_game_start":1434211234,"timestamp_level_start":1434211234},"37746":{"id":37746,"level":100,"players":1003,"active_players":302,"clicks":"2121978","abilities":"479","status":2,"timestamp":1434215279,"timestamp_game_start":1434213832,"timestamp_level_start":1434215264},"37678":{"id":37678,"level":171,"players":1022,"active_players":244,"clicks":"388574885163","abilities":"978","status":2,"timestamp":1434215279,"timestamp_game_start":1434212859,"timestamp_level_start":1434215263},"37735":{"id":37735,"level":120,"players":1007,"active_players":298,"clicks":"2799603","abilities":"564","status":2,"timestamp":1434215279,"timestamp_game_start":1434213750,"timestamp_level_start":1434215272},"37516":{"id":37516,"level":9,"players":731,"active_players":413,"clicks":"568233","abilities":"25","status":3,"timestamp":1434211201,"timestamp_game_start":1434210815,"timestamp_level_start":1434211098},"37543":{"id":37543,"level":0,"players":0,"active_players":57,"clicks":null,"abilities":null,"status":3,"timestamp":1434211250,"timestamp_game_start":1434211250,"timestamp_level_start":1434211250},"37643":{"id":37643,"level":200,"players":1033,"active_players":242,"clicks":"4444143","abilities":"1208","status":2,"timestamp":1434215279,"timestamp_game_start":1434212466,"timestamp_level_start":1434215264},"37633":{"id":37633,"level":211,"players":1035,"active_players":218,"clicks":"4899006","abilities":"1231","status":2,"timestamp":1434215279,"timestamp_game_start":1434212387,"timestamp_level_start":1434215265},"37578":{"id":37578,"level":452,"players":1499,"active_players":657,"clicks":"10896297","abilities":"3460","status":2,"timestamp":1434215279,"timestamp_game_start":1434211822,"timestamp_level_start":1434215278},"37847":{"id":37847,"level":14,"players":998,"active_players":566,"clicks":"434259","abilities":"22","status":2,"timestamp":1434215279,"timestamp_game_start":1434215034,"timestamp_level_start":1434215279},"37604":{"id":37604,"level":257,"players":1064,"active_players":317,"clicks":"6158815","abilities":"1633","status":2,"timestamp":1434215279,"timestamp_game_start":1434212103,"timestamp_level_start":1434215279},"37830":{"id":37830,"level":46,"players":1000,"active_players":435,"clicks":"1120369","abilities":"123","status":2,"timestamp":1434215279,"timestamp_game_start":1434214618,"timestamp_level_start":1434215275},"37625":{"id":37625,"level":239,"players":1113,"active_players":265,"clicks":"4838194","abilities":"1418","status":2,"timestamp":1434215279,"timestamp_game_start":1434212391,"timestamp_level_start":1434215262},"37663":{"id":37663,"level":180,"players":1024,"active_players":231,"clicks":"3866552","abilities":"1007","status":2,"timestamp":1434215279,"timestamp_game_start":1434212836,"timestamp_level_start":1434215276},"37788":{"id":37788,"level":75,"players":1002,"active_players":381,"clicks":"1925865","abilities":"271","status":2,"timestamp":1434215279,"timestamp_game_start":1434214263,"timestamp_level_start":1434215273},"37709":{"id":37709,"level":138,"players":1011,"active_players":233,"clicks":"3466690","abilities":"760","status":2,"timestamp":1434215279,"timestamp_game_start":1434213200,"timestamp_level_start":1434215239},"37745":{"id":37745,"level":114,"players":1020,"active_players":295,"clicks":"2710345","abilities":"596","status":2,"timestamp":1434215279,"timestamp_game_start":1434213681,"timestamp_level_start":1434215263},"37781":{"id":37781,"level":76,"players":1013,"active_players":320,"clicks":"1703912","abilities":"312","status":2,"timestamp":1434215279,"timestamp_game_start":1434214201,"timestamp_level_start":1434215270},"37644":{"id":37644,"level":217,"players":1033,"active_players":220,"clicks":"4403912","abilities":"1198","status":2,"timestamp":1434215279,"timestamp_game_start":1434212416,"timestamp_level_start":1434215269},"37672":{"id":37672,"level":186,"players":1011,"active_players":234,"clicks":"3809997","abilities":"1056","status":2,"timestamp":1434215279,"timestamp_game_start":1434212842,"timestamp_level_start":1434215265},"37819":{"id":37819,"level":51,"players":1000,"active_players":466,"clicks":"1198572","abilities":"165","status":2,"timestamp":1434215279,"timestamp_game_start":1434214618,"timestamp_level_start":1434215272},"37725":{"id":37725,"level":136,"players":1027,"active_players":251,"clicks":"3254023","abilities":"784","status":2,"timestamp":1434215279,"timestamp_game_start":1434213309,"timestamp_level_start":1434215266},"37856":{"id":37856,"level":6,"players":998,"active_players":563,"clicks":"143682","abilities":"7","status":2,"timestamp":1434215279,"timestamp_game_start":1434215144,"timestamp_level_start":1434215279},"37585":{"id":37585,"level":342,"players":1192,"active_players":389,"clicks":"7942664","abilities":"2426","status":2,"timestamp":1434215279,"timestamp_game_start":1434211833,"timestamp_level_start":1434215264},"37817":{"id":37817,"level":39,"players":1000,"active_players":429,"clicks":"1038429","abilities":"95","status":2,"timestamp":1434215279,"timestamp_game_start":1434214721,"timestamp_level_start":1434215277},"37862":{"id":37862,"level":7,"players":992,"active_players":530,"clicks":"209583","abilities":"13","status":2,"timestamp":1434215279,"timestamp_game_start":1434215106,"timestamp_level_start":1434215267},"37676":{"id":37676,"level":158,"players":1021,"active_players":203,"clicks":"3645076","abilities":"925","status":2,"timestamp":1434215279,"timestamp_game_start":1434212791,"timestamp_level_start":1434215262},"37816":{"id":37816,"level":30,"players":1010,"active_players":491,"clicks":"754208","abilities":"62","status":2,"timestamp":1434215279,"timestamp_game_start":1434214824,"timestamp_level_start":1434215270},"37564":{"id":37564,"level":319,"players":1063,"active_players":349,"clicks":"6950182","abilities":"2036","status":2,"timestamp":1434215279,"timestamp_game_start":1434212116,"timestamp_level_start":1434215264},"37612":{"id":37612,"level":233,"players":1060,"active_players":285,"clicks":"5562632","abilities":"1558","status":2,"timestamp":1434215279,"timestamp_game_start":1434212115,"timestamp_level_start":1434215273},"37626":{"id":37626,"level":203,"players":1041,"active_players":255,"clicks":"4268598","abilities":"1167","status":2,"timestamp":1434215279,"timestamp_game_start":1434212436,"timestamp_level_start":1434215266},"37713":{"id":37713,"level":137,"players":1021,"active_players":210,"clicks":"2744800","abilities":"718","status":2,"timestamp":1434215279,"timestamp_game_start":1434213210,"timestamp_level_start":1434215272},"37780":{"id":37780,"level":69,"players":991,"active_players":370,"clicks":"1564381","abilities":"294","status":2,"timestamp":1434215279,"timestamp_game_start":1434214287,"timestamp_level_start":1434215265},"37685":{"id":37685,"level":186,"players":1035,"active_players":228,"clicks":"3670081","abilities":"1111","status":2,"timestamp":1434215279,"timestamp_game_start":1434212823,"timestamp_level_start":1434215262},"37691":{"id":37691,"level":167,"players":1063,"active_players":211,"clicks":"3532812","abilities":"930","status":2,"timestamp":1434215279,"timestamp_game_start":1434212724,"timestamp_level_start":1434215279},"37620":{"id":37620,"level":249,"players":1117,"active_players":295,"clicks":"6412346","abilities":"1480","status":2,"timestamp":1434215279,"timestamp_game_start":1434212117,"timestamp_level_start":1434215269},"37642":{"id":37642,"level":196,"players":1039,"active_players":245,"clicks":"4378481","abilities":"1198","status":2,"timestamp":1434215279,"timestamp_game_start":1434212452,"timestamp_level_start":1434215260},"37616":{"id":37616,"level":264,"players":1048,"active_players":279,"clicks":"5412824","abilities":"1773","status":2,"timestamp":1434215279,"timestamp_game_start":1434212116,"timestamp_level_start":1434215275},"37793":{"id":37793,"level":75,"players":994,"active_players":354,"clicks":"1736898","abilities":"302","status":2,"timestamp":1434215279,"timestamp_game_start":1434214251,"timestamp_level_start":1434215269},"37590":{"id":37590,"level":272,"players":1059,"active_players":288,"clicks":"6881844","abilities":"1642","status":2,"timestamp":1434215279,"timestamp_game_start":1434212099,"timestamp_level_start":1434215273},"37619":{"id":37619,"level":249,"players":1084,"active_players":296,"clicks":"5286333","abilities":"1582","status":2,"timestamp":1434215279,"timestamp_game_start":1434212076,"timestamp_level_start":1434215277},"37529":{"id":37529,"level":0,"players":0,"active_players":193,"clicks":null,"abilities":null,"status":3,"timestamp":1434211304,"timestamp_game_start":1434211304,"timestamp_level_start":1434211304},"37650":{"id":37650,"level":209,"players":1013,"active_players":226,"clicks":"4535805","abilities":"1229","status":2,"timestamp":1434215279,"timestamp_game_start":1434212366,"timestamp_level_start":1434215229},"37730":{"id":37730,"level":131,"players":1011,"active_players":243,"clicks":"2858099","abilities":"697","status":2,"timestamp":1434215279,"timestamp_game_start":1434213236,"timestamp_level_start":1434215263},"37515":{"id":37515,"level":31,"players":756,"active_players":371,"clicks":"827955","abilities":"88","status":3,"timestamp":1434211201,"timestamp_game_start":1434210528,"timestamp_level_start":1434211199},"37523":{"id":37523,"level":0,"players":766,"active_players":347,"clicks":"33217","abilities":null,"status":3,"timestamp":1434211201,"timestamp_game_start":1434211171,"timestamp_level_start":1434211171},"37838":{"id":37838,"level":39,"players":1002,"active_players":465,"clicks":"845367","abilities":"124","status":2,"timestamp":1434215279,"timestamp_game_start":1434214737,"timestamp_level_start":1434215265},"37839":{"id":37839,"level":37,"players":1005,"active_players":475,"clicks":"874786","abilities":"99","status":2,"timestamp":1434215279,"timestamp_game_start":1434214747,"timestamp_level_start":1434215279},"37555":{"id":37555,"level":430,"players":1411,"active_players":577,"clicks":"417473991985","abilities":"2828","status":2,"timestamp":1434215279,"timestamp_game_start":1434211843,"timestamp_level_start":1434215273},"37841":{"id":37841,"level":1,"players":990,"active_players":398,"clicks":"47708","abilities":null,"status":2,"timestamp":1434215279,"timestamp_game_start":1434215219,"timestamp_level_start":1434215264},"37632":{"id":37632,"level":216,"players":1053,"active_players":214,"clicks":"4152464","abilities":"1496","status":2,"timestamp":1434215279,"timestamp_game_start":1434212366,"timestamp_level_start":1434215277},"37722":{"id":37722,"level":139,"players":1009,"active_players":221,"clicks":"3482709","abilities":"752","status":2,"timestamp":1434215279,"timestamp_game_start":1434213153,"timestamp_level_start":1434215234},"37591":{"id":37591,"level":219,"players":1030,"active_players":219,"clicks":"4775752","abilities":"1553","status":2,"timestamp":1434215279,"timestamp_game_start":1434212100,"timestamp_level_start":1434215217},"37610":{"id":37610,"level":271,"players":1080,"active_players":310,"clicks":"5502885","abilities":"1870","status":2,"timestamp":1434215279,"timestamp_game_start":1434212086,"timestamp_level_start":1434215276},"37652":{"id":37652,"level":220,"players":1039,"active_players":272,"clicks":"4743772","abilities":"1184","status":2,"timestamp":1434215279,"timestamp_game_start":1434212449,"timestamp_level_start":1434215265},"37777":{"id":37777,"level":136,"players":1500,"active_players":769,"clicks":"3489992","abilities":"802","status":2,"timestamp":1434215279,"timestamp_game_start":1434214234,"timestamp_level_start":1434215277},"37837":{"id":37837,"level":39,"players":1003,"active_players":451,"clicks":"945570","abilities":"139","status":2,"timestamp":1434215279,"timestamp_game_start":1434214720,"timestamp_level_start":1434215263},"37677":{"id":37677,"level":150,"players":1032,"active_players":189,"clicks":"3355078","abilities":"808","status":2,"timestamp":1434215279,"timestamp_game_start":1434212783,"timestamp_level_start":1434215275},"37804":{"id":37804,"level":42,"players":990,"active_players":424,"clicks":"1003627","abilities":"141","status":2,"timestamp":1434215279,"timestamp_game_start":1434214671,"timestamp_level_start":1434215266},"37594":{"id":37594,"level":266,"players":1062,"active_players":300,"clicks":"6284155","abilities":"1632","status":2,"timestamp":1434215279,"timestamp_game_start":1434212052,"timestamp_level_start":1434215274},"37849":{"id":37849,"level":7,"players":1000,"active_players":573,"clicks":"199283","abilities":"6","status":2,"timestamp":1434215279,"timestamp_game_start":1434215117,"timestamp_level_start":1434215275},"37867":{"id":37867,"level":13,"players":1007,"active_players":534,"clicks":"438058","abilities":"22","status":2,"timestamp":1434215279,"timestamp_game_start":1434215014,"timestamp_level_start":1434215272},"37586":{"id":37586,"level":405,"players":1300,"active_players":479,"clicks":"15556942","abilities":"2869","status":2,"timestamp":1434215279,"timestamp_game_start":1434211840,"timestamp_level_start":1434215271},"37760":{"id":37760,"level":99,"players":1029,"active_players":312,"clicks":"2130917","abilities":"530","status":2,"timestamp":1434215279,"timestamp_game_start":1434213825,"timestamp_level_start":1434215240},"37547":{"id":37547,"level":0,"players":0,"active_players":216,"clicks":null,"abilities":null,"status":3,"timestamp":1434211276,"timestamp_game_start":1434211276,"timestamp_level_start":1434211276},"37613":{"id":37613,"level":311,"players":1105,"active_players":367,"clicks":"7524862","abilities":"2031","status":2,"timestamp":1434215279,"timestamp_game_start":1434212042,"timestamp_level_start":1434215275},"37795":{"id":37795,"level":90,"players":1011,"active_players":314,"clicks":"2012815","abilities":"414","status":2,"timestamp":1434215279,"timestamp_game_start":1434214006,"timestamp_level_start":1434215261},"37846":{"id":37846,"level":9,"players":991,"active_players":511,"clicks":"247172","abilities":"10","status":2,"timestamp":1434215279,"timestamp_game_start":1434215076,"timestamp_level_start":1434215276},"37687":{"id":37687,"level":205,"players":1070,"active_players":263,"clicks":"4405834","abilities":"1097","status":2,"timestamp":1434215279,"timestamp_game_start":1434212617,"timestamp_level_start":1434215278},"37782":{"id":37782,"level":72,"players":999,"active_players":352,"clicks":"1571508","abilities":"223","status":2,"timestamp":1434215279,"timestamp_game_start":1434214364,"timestamp_level_start":1434215277},"37565":{"id":37565,"level":369,"players":1253,"active_players":426,"clicks":"8415870","abilities":"2970","status":2,"timestamp":1434215279,"timestamp_game_start":1434211825,"timestamp_level_start":1434215234},"37814":{"id":37814,"level":49,"players":1013,"active_players":419,"clicks":"1221804","abilities":"175","status":2,"timestamp":1434215279,"timestamp_game_start":1434214599,"timestamp_level_start":1434215265},"37506":{"id":37506,"level":74,"players":0,"active_players":271,"clicks":"1746958","abilities":"373","status":3,"timestamp":1434211201,"timestamp_game_start":1434209685,"timestamp_level_start":1434211200},"37870":{"id":37870,"level":9,"players":992,"active_players":579,"clicks":"289815","abilities":"14","status":2,"timestamp":1434215279,"timestamp_game_start":1434215091,"timestamp_level_start":1434215268},"37621":{"id":37621,"level":357,"players":1110,"active_players":339,"clicks":"20158935","abilities":"1984","status":2,"timestamp":1434215279,"timestamp_game_start":1434212064,"timestamp_level_start":1434215272},"37785":{"id":37785,"level":67,"players":1007,"active_players":362,"clicks":"1511685","abilities":"224","status":2,"timestamp":1434215279,"timestamp_game_start":1434214262,"timestamp_level_start":1434215266},"37622":{"id":37622,"level":260,"players":1109,"active_players":320,"clicks":"5842212","abilities":"1749","status":2,"timestamp":1434215279,"timestamp_game_start":1434212089,"timestamp_level_start":1434215274},"37705":{"id":37705,"level":155,"players":1022,"active_players":255,"clicks":"3148045","abilities":"757","status":2,"timestamp":1434215279,"timestamp_game_start":1434213235,"timestamp_level_start":1434215262},"37774":{"id":37774,"level":87,"players":989,"active_players":334,"clicks":"2012578","abilities":"358","status":2,"timestamp":1434215279,"timestamp_game_start":1434214137,"timestamp_level_start":1434215275},"37549":{"id":37549,"level":0,"players":0,"active_players":0,"clicks":null,"abilities":null,"status":3,"timestamp":1434211614,"timestamp_game_start":1434211289,"timestamp_level_start":1434211289},"37640":{"id":37640,"level":187,"players":1024,"active_players":217,"clicks":"3770243","abilities":"1172","status":2,"timestamp":1434215279,"timestamp_game_start":1434212429,"timestamp_level_start":1434215263},"37726":{"id":37726,"level":147,"players":1028,"active_players":242,"clicks":"3171820","abilities":"721","status":2,"timestamp":1434215279,"timestamp_game_start":1434213218,"timestamp_level_start":1434215267},"37617":{"id":37617,"level":262,"players":1092,"active_players":291,"clicks":"5622705","abilities":"1767","status":2,"timestamp":1434215279,"timestamp_game_start":1434212106,"timestamp_level_start":1434215279},"37651":{"id":37651,"level":688,"players":1500,"active_players":866,"clicks":"1489414448927","abilities":"5396","status":2,"timestamp":1434215279,"timestamp_game_start":1434212252,"timestamp_level_start":1434215278},"37832":{"id":37832,"level":21,"players":1002,"active_players":505,"clicks":"666739","abilities":"52","status":2,"timestamp":1434215279,"timestamp_game_start":1434214890,"timestamp_level_start":1434215275},"37596":{"id":37596,"level":272,"players":1087,"active_players":296,"clicks":"6090563","abilities":"1952","status":2,"timestamp":1434215279,"timestamp_game_start":1434212065,"timestamp_level_start":1434215275},"37679":{"id":37679,"level":166,"players":1020,"active_players":233,"clicks":"3497523","abilities":"941","status":2,"timestamp":1434215279,"timestamp_game_start":1434212876,"timestamp_level_start":1434215264},"37864":{"id":37864,"level":1,"players":1000,"active_players":313,"clicks":"35307","abilities":null,"status":2,"timestamp":1434215279,"timestamp_game_start":1434215229,"timestamp_level_start":1434215275},"37638":{"id":37638,"level":220,"players":1060,"active_players":275,"clicks":"4799214","abilities":"1321","status":2,"timestamp":1434215279,"timestamp_game_start":1434212441,"timestamp_level_start":1434215267},"37783":{"id":37783,"level":90,"players":991,"active_players":316,"clicks":"1952859","abilities":"399","status":2,"timestamp":1434215279,"timestamp_game_start":1434214105,"timestamp_level_start":1434215277},"37768":{"id":37768,"level":82,"players":992,"active_players":337,"clicks":"1803741","abilities":"362","status":2,"timestamp":1434215279,"timestamp_game_start":1434214138,"timestamp_level_start":1434215272},"37787":{"id":37787,"level":66,"players":995,"active_players":353,"clicks":"1509279","abilities":"235","status":2,"timestamp":1434215279,"timestamp_game_start":1434214335,"timestamp_level_start":1434215267},"37836":{"id":37836,"level":26,"players":994,"active_players":451,"clicks":"593402","abilities":"66","status":2,"timestamp":1434215279,"timestamp_game_start":1434214834,"timestamp_level_start":1434215273},"37770":{"id":37770,"level":69,"players":1025,"active_players":387,"clicks":"1512045","abilities":"278","status":2,"timestamp":1434215279,"timestamp_game_start":1434214257,"timestamp_level_start":1434215236},"37731":{"id":37731,"level":150,"players":1033,"active_players":252,"clicks":"3464839","abilities":"785","status":2,"timestamp":1434215279,"timestamp_game_start":1434213237,"timestamp_level_start":1434215278},"37666":{"id":37666,"level":159,"players":1036,"active_players":223,"clicks":"3549950","abilities":"903","status":2,"timestamp":1434215279,"timestamp_game_start":1434212723,"timestamp_level_start":1434215216},"37532":{"id":37532,"level":0,"players":0,"active_players":51,"clicks":null,"abilities":null,"status":3,"timestamp":1434211264,"timestamp_game_start":1434211264,"timestamp_level_start":1434211264},"37659":{"id":37659,"level":189,"players":1041,"active_players":233,"clicks":"4077271","abilities":"1087","status":2,"timestamp":1434215279,"timestamp_game_start":1434212423,"timestamp_level_start":1434215229},"37588":{"id":37588,"level":286,"players":1107,"active_players":323,"clicks":"6412611","abilities":"2006","status":2,"timestamp":1434215279,"timestamp_game_start":1434212074,"timestamp_level_start":1434215266},"37641":{"id":37641,"level":202,"players":1046,"active_players":248,"clicks":"4235029","abilities":"1206","status":2,"timestamp":1434215279,"timestamp_game_start":1434212404,"timestamp_level_start":1434215273},"37738":{"id":37738,"level":122,"players":1009,"active_players":257,"clicks":"2847196","abilities":"600","status":2,"timestamp":1434215279,"timestamp_game_start":1434213621,"timestamp_level_start":1434215262},"37875":{"id":37875,"level":5,"players":1003,"active_players":546,"clicks":"187639","abilities":"2","status":2,"timestamp":1434215279,"timestamp_game_start":1434215152,"timestamp_level_start":1434215277},"37627":{"id":37627,"level":217,"players":1122,"active_players":224,"clicks":"4579528","abilities":"1188","status":2,"timestamp":1434215279,"timestamp_game_start":1434212430,"timestamp_level_start":1434215278},"37845":{"id":37845,"level":7,"players":995,"active_players":580,"clicks":"183980","abilities":"8","status":2,"timestamp":1434215279,"timestamp_game_start":1434215117,"timestamp_level_start":1434215274},"37762":{"id":37762,"level":109,"players":1008,"active_players":285,"clicks":"2462009","abilities":"557","status":2,"timestamp":1434215279,"timestamp_game_start":1434213699,"timestamp_level_start":1434215250},"37772":{"id":37772,"level":76,"players":999,"active_players":353,"clicks":"1802313","abilities":"328","status":2,"timestamp":1434215279,"timestamp_game_start":1434214195,"timestamp_level_start":1434215273},"37792":{"id":37792,"level":70,"players":1023,"active_players":367,"clicks":"1660963","abilities":"232","status":2,"timestamp":1434215279,"timestamp_game_start":1434214329,"timestamp_level_start":1434215268},"37607":{"id":37607,"level":306,"players":1069,"active_players":358,"clicks":"8303172","abilities":"1980","status":2,"timestamp":1434215279,"timestamp_game_start":1434212027,"timestamp_level_start":1434215271},"37789":{"id":37789,"level":85,"players":1001,"active_players":328,"clicks":"1913621","abilities":"311","status":2,"timestamp":1434215279,"timestamp_game_start":1434214192,"timestamp_level_start":1434215265},"37645":{"id":37645,"level":519,"players":1500,"active_players":649,"clicks":"13922275","abilities":"4104","status":2,"timestamp":1434215279,"timestamp_game_start":1434212392,"timestamp_level_start":1434215277},"37511":{"id":37511,"level":4,"players":0,"active_players":418,"clicks":"145193","abilities":"1","status":3,"timestamp":1434211201,"timestamp_game_start":1434211076,"timestamp_level_start":1434211193},"37628":{"id":37628,"level":182,"players":1172,"active_players":242,"clicks":"3923989","abilities":"1148","status":2,"timestamp":1434215279,"timestamp_game_start":1434212396,"timestamp_level_start":1434215279},"37828":{"id":37828,"level":28,"players":985,"active_players":489,"clicks":"643100","abilities":"66","status":2,"timestamp":1434215279,"timestamp_game_start":1434214850,"timestamp_level_start":1434215274},"37866":{"id":37866,"level":10,"players":987,"active_players":549,"clicks":"381853","abilities":"12","status":2,"timestamp":1434215279,"timestamp_game_start":1434215038,"timestamp_level_start":1434215272},"37715":{"id":37715,"level":120,"players":1014,"active_players":249,"clicks":"2581124","abilities":"660","status":2,"timestamp":1434215279,"timestamp_game_start":1434213335,"timestamp_level_start":1434215274},"37794":{"id":37794,"level":92,"players":1015,"active_players":343,"clicks":"2793095","abilities":"373","status":2,"timestamp":1434215279,"timestamp_game_start":1434214119,"timestamp_level_start":1434215269},"37786":{"id":37786,"level":79,"players":998,"active_players":375,"clicks":"1883401","abilities":"292","status":2,"timestamp":1434215279,"timestamp_game_start":1434214344,"timestamp_level_start":1434215268},"37766":{"id":37766,"level":112,"players":1024,"active_players":299,"clicks":"2361854","abilities":"574","status":2,"timestamp":1434215279,"timestamp_game_start":1434213701,"timestamp_level_start":1434215265},"37706":{"id":37706,"level":182,"players":1035,"active_players":256,"clicks":"5269128","abilities":"878","status":2,"timestamp":1434215279,"timestamp_game_start":1434213174,"timestamp_level_start":1434215269},"37728":{"id":37728,"level":156,"players":1010,"active_players":259,"clicks":"3453189","abilities":"821","status":2,"timestamp":1434215279,"timestamp_game_start":1434213302,"timestamp_level_start":1434215279},"37871":{"id":37871,"level":9,"players":990,"active_players":547,"clicks":"273131","abilities":"10","status":2,"timestamp":1434215279,"timestamp_game_start":1434215069,"timestamp_level_start":1434215264},"37860":{"id":37860,"level":3,"players":1001,"active_players":519,"clicks":"118548","abilities":"3","status":2,"timestamp":1434215279,"timestamp_game_start":1434215179,"timestamp_level_start":1434215279},"37695":{"id":37695,"level":182,"players":1064,"active_players":252,"clicks":"4373683","abilities":"979","status":2,"timestamp":1434215279,"timestamp_game_start":1434212793,"timestamp_level_start":1434215273},"37609":{"id":37609,"level":294,"players":1101,"active_players":279,"clicks":"6417097","abilities":"1898","status":2,"timestamp":1434215279,"timestamp_game_start":1434212089,"timestamp_level_start":1434215268},"37630":{"id":37630,"level":213,"players":1042,"active_players":247,"clicks":"4357973","abilities":"1365","status":2,"timestamp":1434215279,"timestamp_game_start":1434212363,"timestamp_level_start":1434215263},"37809":{"id":37809,"level":39,"players":991,"active_players":438,"clicks":"849204","abilities":"94","status":2,"timestamp":1434215279,"timestamp_game_start":1434214724,"timestamp_level_start":1434215278},"37702":{"id":37702,"level":145,"players":1042,"active_players":215,"clicks":"3225644","abilities":"802","status":2,"timestamp":1434215279,"timestamp_game_start":1434213149,"timestamp_level_start":1434215267},"37825":{"id":37825,"level":36,"players":998,"active_players":448,"clicks":"795469","abilities":"92","status":2,"timestamp":1434215279,"timestamp_game_start":1434214696,"timestamp_level_start":1434215272},"37753":{"id":37753,"level":127,"players":1010,"active_players":255,"clicks":"2585265","abilities":"559","status":2,"timestamp":1434215279,"timestamp_game_start":1434213672,"timestamp_level_start":1434215279},"37674":{"id":37674,"level":157,"players":1036,"active_players":211,"clicks":"3857006","abilities":"892","status":2,"timestamp":1434215279,"timestamp_game_start":1434212850,"timestamp_level_start":1434215270},"37767":{"id":37767,"level":108,"players":1017,"active_players":271,"clicks":"2409086","abilities":"496","status":2,"timestamp":1434215279,"timestamp_game_start":1434213732,"timestamp_level_start":1434215276},"37869":{"id":37869,"level":1,"players":995,"active_players":340,"clicks":"31038","abilities":null,"status":2,"timestamp":1434215279,"timestamp_game_start":1434215224,"timestamp_level_start":1434215277},"37822":{"id":37822,"level":25,"players":996,"active_players":473,"clicks":"557355","abilities":"37","status":2,"timestamp":1434215279,"timestamp_game_start":1434214863,"timestamp_level_start":1434215276},"37582":{"id":37582,"level":359,"players":1202,"active_players":452,"clicks":"8283489","abilities":"2783","status":2,"timestamp":1434215279,"timestamp_game_start":1434211832,"timestamp_level_start":1434215264},"37812":{"id":37812,"level":48,"players":995,"active_players":434,"clicks":"1072377","abilities":"160","status":2,"timestamp":1434215279,"timestamp_game_start":1434214626,"timestamp_level_start":1434215277},"37512":{"id":37512,"level":34,"players":767,"active_players":392,"clicks":"921674","abilities":"117","status":3,"timestamp":1434211201,"timestamp_game_start":1434210476,"timestamp_level_start":1434211190},"37583":{"id":37583,"level":394,"players":1262,"active_players":456,"clicks":"8494932","abilities":"2788","status":2,"timestamp":1434215279,"timestamp_game_start":1434211830,"timestamp_level_start":1434215270},"37857":{"id":37857,"level":5,"players":995,"active_players":556,"clicks":"147490","abilities":"1","status":2,"timestamp":1434215279,"timestamp_game_start":1434215151,"timestamp_level_start":1434215276},"37843":{"id":37843,"level":4,"players":994,"active_players":549,"clicks":"142513","abilities":null,"status":2,"timestamp":1434215279,"timestamp_game_start":1434215174,"timestamp_level_start":1434215279},"37757":{"id":37757,"level":108,"players":1003,"active_players":241,"clicks":"2511477","abilities":"524","status":2,"timestamp":1434215279,"timestamp_game_start":1434213767,"timestamp_level_start":1434215278},"37615":{"id":37615,"level":259,"players":1129,"active_players":328,"clicks":"6708486","abilities":"1757","status":2,"timestamp":1434215279,"timestamp_game_start":1434212114,"timestamp_level_start":1434215274},"37686":{"id":37686,"level":179,"players":1014,"active_players":233,"clicks":"4518535","abilities":"1012","status":2,"timestamp":1434215279,"timestamp_game_start":1434212740,"timestamp_level_start":1434215267},"37598":{"id":37598,"level":255,"players":1117,"active_players":292,"clicks":"5864031","abilities":"1751","status":2,"timestamp":1434215279,"timestamp_game_start":1434212071,"timestamp_level_start":1434215263},"37752":{"id":37752,"level":106,"players":1024,"active_players":282,"clicks":"2210241","abilities":"536","status":2,"timestamp":1434215279,"timestamp_game_start":1434213727,"timestamp_level_start":1434215264},"37798":{"id":37798,"level":77,"players":991,"active_players":334,"clicks":"1730607","abilities":"339","status":2,"timestamp":1434215279,"timestamp_game_start":1434214194,"timestamp_level_start":1434215277},"37635":{"id":37635,"level":191,"players":1023,"active_players":247,"clicks":"3995267","abilities":"1272","status":2,"timestamp":1434215279,"timestamp_game_start":1434212416,"timestamp_level_start":1434215270},"37649":{"id":37649,"level":227,"players":1065,"active_players":212,"clicks":"5020519","abilities":"1315","status":2,"timestamp":1434215279,"timestamp_game_start":1434212432,"timestamp_level_start":1434215263},"37606":{"id":37606,"level":295,"players":1120,"active_players":321,"clicks":"7043936","abilities":"2039","status":2,"timestamp":1434215279,"timestamp_game_start":1434211983,"timestamp_level_start":1434215273},"37522":{"id":37522,"level":0,"players":1,"active_players":55,"clicks":null,"abilities":null,"status":3,"timestamp":1434211227,"timestamp_game_start":1434211227,"timestamp_level_start":1434211227},"37554":{"id":37554,"level":525,"players":1500,"active_players":562,"clicks":"13133249","abilities":"4136","status":2,"timestamp":1434215279,"timestamp_game_start":1434211846,"timestamp_level_start":1434215276},"37698":{"id":37698,"level":133,"players":1015,"active_players":227,"clicks":"3069146","abilities":"664","status":2,"timestamp":1434215279,"timestamp_game_start":1434213275,"timestamp_level_start":1434215262},"37648":{"id":37648,"level":234,"players":1028,"active_players":252,"clicks":"5169565","abilities":"1313","status":2,"timestamp":1434215279,"timestamp_game_start":1434212465,"timestamp_level_start":1434215267},"37829":{"id":37829,"level":32,"players":996,"active_players":444,"clicks":"740522","abilities":"74","status":2,"timestamp":1434215279,"timestamp_game_start":1434214782,"timestamp_level_start":1434215272},"37800":{"id":37800,"level":71,"players":1012,"active_players":371,"clicks":"1604639","abilities":"324","status":2,"timestamp":1434215279,"timestamp_game_start":1434214288,"timestamp_level_start":1434215266},"37813":{"id":37813,"level":37,"players":993,"active_players":481,"clicks":"769115","abilities":"94","status":2,"timestamp":1434215279,"timestamp_game_start":1434214741,"timestamp_level_start":1434215275},"37694":{"id":37694,"level":181,"players":1001,"active_players":253,"clicks":"4346853","abilities":"977","status":2,"timestamp":1434215279,"timestamp_game_start":1434212810,"timestamp_level_start":1434215275},"37779":{"id":37779,"level":75,"players":1004,"active_players":327,"clicks":"1613741","abilities":"318","status":2,"timestamp":1434215279,"timestamp_game_start":1434214193,"timestamp_level_start":1434215269},"37739":{"id":37739,"level":123,"players":1009,"active_players":268,"clicks":"2871516","abilities":"641","status":2,"timestamp":1434215279,"timestamp_game_start":1434213578,"timestamp_level_start":1434215265},"37623":{"id":37623,"level":286,"players":1084,"active_players":311,"clicks":"6632106","abilities":"1807","status":2,"timestamp":1434215279,"timestamp_game_start":1434212107,"timestamp_level_start":1434215269},"37732":{"id":37732,"level":110,"players":999,"active_players":274,"clicks":"2755625","abilities":"567","status":2,"timestamp":1434215279,"timestamp_game_start":1434213663,"timestamp_level_start":1434215262},"37824":{"id":37824,"level":31,"players":1003,"active_players":468,"clicks":"857694","abilities":"89","status":2,"timestamp":1434215279,"timestamp_game_start":1434214796,"timestamp_level_start":1434215269},"37858":{"id":37858,"level":0,"players":994,"active_players":211,"clicks":"10622","abilities":null,"status":2,"timestamp":1434215279,"timestamp_game_start":1434215253,"timestamp_level_start":1434215253},"37671":{"id":37671,"level":406,"players":1500,"active_players":580,"clicks":"16164739","abilities":"3080","status":2,"timestamp":1434215279,"timestamp_game_start":1434212795,"timestamp_level_start":1434215276},"37700":{"id":37700,"level":166,"players":1027,"active_players":234,"clicks":"2978471","abilities":"853","status":2,"timestamp":1434215279,"timestamp_game_start":1434213223,"timestamp_level_start":1434215264},"37548":{"id":37548,"level":0,"players":0,"active_players":41,"clicks":null,"abilities":null,"status":3,"timestamp":1434211294,"timestamp_game_start":1434211294,"timestamp_level_start":1434211294},"37560":{"id":37560,"level":493,"players":1500,"active_players":598,"clicks":"11976790","abilities":"3964","status":2,"timestamp":1434215279,"timestamp_game_start":1434211817,"timestamp_level_start":1434215276},"37872":{"id":37872,"level":1,"players":999,"active_players":403,"clicks":"63333","abilities":null,"status":2,"timestamp":1434215279,"timestamp_game_start":1434215210,"timestamp_level_start":1434215265},"37503":{"id":37503,"level":0,"players":0,"active_players":46,"clicks":null,"abilities":null,"status":3,"timestamp":1434211234,"timestamp_game_start":1434211234,"timestamp_level_start":1434211234},"37761":{"id":37761,"level":108,"players":1014,"active_players":283,"clicks":"2370136","abilities":"430","status":2,"timestamp":1434215279,"timestamp_game_start":1434213808,"timestamp_level_start":1434215256},"37808":{"id":37808,"level":39,"players":996,"active_players":461,"clicks":"970749","abilities":"90","status":2,"timestamp":1434215279,"timestamp_game_start":1434214709,"timestamp_level_start":1434215272},"37851":{"id":37851,"level":9,"players":990,"active_players":558,"clicks":"278417","abilities":"13","status":2,"timestamp":1434215279,"timestamp_game_start":1434215067,"timestamp_level_start":1434215256},"37573":{"id":37573,"level":390,"players":1230,"active_players":432,"clicks":"9119722","abilities":"2908","status":2,"timestamp":1434215279,"timestamp_game_start":1434211842,"timestamp_level_start":1434215279},"37599":{"id":37599,"level":290,"players":1088,"active_players":285,"clicks":"6919648","abilities":"1730","status":2,"timestamp":1434215279,"timestamp_game_start":1434212088,"timestamp_level_start":1434215274},"37743":{"id":37743,"level":106,"players":1022,"active_players":300,"clicks":"2343393","abilities":"521","status":2,"timestamp":1434215279,"timestamp_game_start":1434213712,"timestamp_level_start":1434215269},"37863":{"id":37863,"level":9,"players":994,"active_players":567,"clicks":"242196","abilities":"10","status":2,"timestamp":1434215279,"timestamp_game_start":1434215093,"timestamp_level_start":1434215266},"37815":{"id":37815,"level":41,"players":999,"active_players":444,"clicks":"844982","abilities":"122","status":2,"timestamp":1434215279,"timestamp_game_start":1434214675,"timestamp_level_start":1434215271},"37639":{"id":37639,"level":275,"players":1064,"active_players":269,"clicks":"22448240","abilities":"1472","status":2,"timestamp":1434215279,"timestamp_game_start":1434212385,"timestamp_level_start":1434215266},"37669":{"id":37669,"level":155,"players":1024,"active_players":219,"clicks":"3278207","abilities":"775","status":2,"timestamp":1434215279,"timestamp_game_start":1434212796,"timestamp_level_start":1434215262},"37611":{"id":37611,"level":310,"players":1066,"active_players":324,"clicks":"6646210","abilities":"1759","status":2,"timestamp":1434215279,"timestamp_game_start":1434212080,"timestamp_level_start":1434215273},"37791":{"id":37791,"level":73,"players":1017,"active_players":354,"clicks":"1681753","abilities":"307","status":2,"timestamp":1434215279,"timestamp_game_start":1434214209,"timestamp_level_start":1434215276},"37595":{"id":37595,"level":270,"players":1043,"active_players":299,"clicks":"5569911","abilities":"1747","status":2,"timestamp":1434215279,"timestamp_game_start":1434212000,"timestamp_level_start":1434215267},"37724":{"id":37724,"level":129,"players":1006,"active_players":217,"clicks":"2740866","abilities":"711","status":2,"timestamp":1434215279,"timestamp_game_start":1434213311,"timestamp_level_start":1434215240},"37827":{"id":37827,"level":40,"players":999,"active_players":453,"clicks":"998703","abilities":"121","status":2,"timestamp":1434215279,"timestamp_game_start":1434214696,"timestamp_level_start":1434215274},"37682":{"id":37682,"level":160,"players":1038,"active_players":241,"clicks":"3694292","abilities":"881","status":2,"timestamp":1434215279,"timestamp_game_start":1434212793,"timestamp_level_start":1434215267},"37569":{"id":37569,"level":529,"players":1500,"active_players":549,"clicks":"135159428","abilities":"4219","status":2,"timestamp":1434215279,"timestamp_game_start":1434211837,"timestamp_level_start":1434215270},"37681":{"id":37681,"level":230,"players":1042,"active_players":217,"clicks":"879705106249","abilities":"894","status":2,"timestamp":1434215279,"timestamp_game_start":1434212761,"timestamp_level_start":1434215266},"37710":{"id":37710,"level":122,"players":1010,"active_players":247,"clicks":"2733470","abilities":"644","status":2,"timestamp":1434215279,"timestamp_game_start":1434213335,"timestamp_level_start":1434215270},"37575":{"id":37575,"level":371,"players":1359,"active_players":506,"clicks":"10034244","abilities":"3067","status":2,"timestamp":1434215279,"timestamp_game_start":1434211827,"timestamp_level_start":1434215271},"37850":{"id":37850,"level":14,"players":1009,"active_players":531,"clicks":"412646","abilities":"26","status":2,"timestamp":1434215279,"timestamp_game_start":1434215001,"timestamp_level_start":1434215279},"37602":{"id":37602,"level":331,"players":1129,"active_players":387,"clicks":"15640711","abilities":"2266","status":2,"timestamp":1434215279,"timestamp_game_start":1434211982,"timestamp_level_start":1434215270},"37513":{"id":37513,"level":0,"players":0,"active_players":47,"clicks":null,"abilities":null,"status":3,"timestamp":1434211228,"timestamp_game_start":1434211228,"timestamp_level_start":1434211228},"37665":{"id":37665,"level":192,"players":1048,"active_players":260,"clicks":"4183768","abilities":"1152","status":2,"timestamp":1434215279,"timestamp_game_start":1434212751,"timestamp_level_start":1434215266},"37629":{"id":37629,"level":201,"players":1040,"active_players":220,"clicks":"4003435","abilities":"1171","status":2,"timestamp":1434215279,"timestamp_game_start":1434212367,"timestamp_level_start":1434215265},"37854":{"id":37854,"level":0,"players":999,"active_players":236,"clicks":"18147","abilities":null,"status":2,"timestamp":1434215279,"timestamp_game_start":1434215246,"timestamp_level_start":1434215246},"37664":{"id":37664,"level":159,"players":1020,"active_players":218,"clicks":"3280466","abilities":"850","status":2,"timestamp":1434215279,"timestamp_game_start":1434212782,"timestamp_level_start":1434215241},"37818":{"id":37818,"level":25,"players":1000,"active_players":507,"clicks":"626164","abilities":"53","status":2,"timestamp":1434215279,"timestamp_game_start":1434214870,"timestamp_level_start":1434215271},"37723":{"id":37723,"level":153,"players":1028,"active_players":234,"clicks":"3290246","abilities":"863","status":2,"timestamp":1434215279,"timestamp_game_start":1434213027,"timestamp_level_start":1434215264},"37690":{"id":37690,"level":195,"players":1036,"active_players":249,"clicks":"4122791","abilities":"1082","status":2,"timestamp":1434215279,"timestamp_game_start":1434212786,"timestamp_level_start":1434215264},"37637":{"id":37637,"level":235,"players":1038,"active_players":255,"clicks":"5053219","abilities":"1368","status":2,"timestamp":1434215279,"timestamp_game_start":1434212372,"timestamp_level_start":1434215276},"37683":{"id":37683,"level":187,"players":1031,"active_players":217,"clicks":"4271445","abilities":"932","status":2,"timestamp":1434215279,"timestamp_game_start":1434212775,"timestamp_level_start":1434215263},"37688":{"id":37688,"level":176,"players":1039,"active_players":241,"clicks":"4071214","abilities":"1100","status":2,"timestamp":1434215279,"timestamp_game_start":1434212851,"timestamp_level_start":1434215262},"37509":{"id":37509,"level":0,"players":0,"active_players":45,"clicks":null,"abilities":null,"status":3,"timestamp":1434211255,"timestamp_game_start":1434211255,"timestamp_level_start":1434211255},"37576":{"id":37576,"level":353,"players":1276,"active_players":389,"clicks":"8384126","abilities":"2524","status":2,"timestamp":1434215279,"timestamp_game_start":1434211848,"timestamp_level_start":1434215273},"37539":{"id":37539,"level":0,"players":0,"active_players":132,"clicks":null,"abilities":null,"status":3,"timestamp":1434211300,"timestamp_game_start":1434211300,"timestamp_level_start":1434211300},"37741":{"id":37741,"level":114,"players":1019,"active_players":259,"clicks":"2657020","abilities":"525","status":2,"timestamp":1434215279,"timestamp_game_start":1434213723,"timestamp_level_start":1434215265},"37692":{"id":37692,"level":177,"players":1018,"active_players":219,"clicks":"4030735","abilities":"949","status":2,"timestamp":1434215279,"timestamp_game_start":1434212853,"timestamp_level_start":1434215266},"37737":{"id":37737,"level":111,"players":1017,"active_players":259,"clicks":"2307503","abilities":"547","status":2,"timestamp":1434215279,"timestamp_game_start":1434213680,"timestamp_level_start":1434215274},"37749":{"id":37749,"level":123,"players":1012,"active_players":289,"clicks":"2808686","abilities":"545","status":2,"timestamp":1434215279,"timestamp_game_start":1434213724,"timestamp_level_start":1434215269},"37773":{"id":37773,"level":82,"players":1005,"active_players":351,"clicks":"1679494","abilities":"337","status":2,"timestamp":1434215279,"timestamp_game_start":1434214181,"timestamp_level_start":1434215275},"37562":{"id":37562,"level":421,"players":1500,"active_players":542,"clicks":"9841063","abilities":"3188","status":2,"timestamp":1434215279,"timestamp_game_start":1434211817,"timestamp_level_start":1434215276},"37689":{"id":37689,"level":141,"players":1017,"active_players":200,"clicks":"3130439","abilities":"853","status":2,"timestamp":1434215279,"timestamp_game_start":1434212870,"timestamp_level_start":1434215264},"37802":{"id":37802,"level":74,"players":984,"active_players":355,"clicks":"1645592","abilities":"351","status":2,"timestamp":1434215279,"timestamp_game_start":1434214207,"timestamp_level_start":1434215264},"37755":{"id":37755,"level":118,"players":1041,"active_players":248,"clicks":"2522035","abilities":"566","status":2,"timestamp":1434215279,"timestamp_game_start":1434213688,"timestamp_level_start":1434215271},"37580":{"id":37580,"level":389,"players":1299,"active_players":466,"clicks":"9710230","abilities":"2696","status":2,"timestamp":1434215279,"timestamp_game_start":1434211837,"timestamp_level_start":1434215270},"37861":{"id":37861,"level":6,"players":1006,"active_players":574,"clicks":"210291","abilities":"5","status":2,"timestamp":1434215279,"timestamp_game_start":1434215113,"timestamp_level_start":1434215270},"37810":{"id":37810,"level":50,"players":997,"active_players":444,"clicks":"1244137","abilities":"145","status":2,"timestamp":1434215279,"timestamp_game_start":1434214656,"timestamp_level_start":1434215278},"37704":{"id":37704,"level":149,"players":1029,"active_players":246,"clicks":"3111990","abilities":"758","status":2,"timestamp":1434215279,"timestamp_game_start":1434213149,"timestamp_level_start":1434215215},"37729":{"id":37729,"level":135,"players":1028,"active_players":239,"clicks":"3152973","abilities":"659","status":2,"timestamp":1434215279,"timestamp_game_start":1434213225,"timestamp_level_start":1434215269},"37833":{"id":37833,"level":28,"players":1004,"active_players":498,"clicks":"651375","abilities":"69","status":2,"timestamp":1434215279,"timestamp_game_start":1434214838,"timestamp_level_start":1434215273},"37584":{"id":37584,"level":609,"players":1500,"active_players":613,"clicks":"186779188633","abilities":"4716","status":2,"timestamp":1434215279,"timestamp_game_start":1434211844,"timestamp_level_start":1434215275},"37540":{"id":37540,"level":0,"players":0,"active_players":206,"clicks":null,"abilities":null,"status":3,"timestamp":1434211284,"timestamp_game_start":1434211284,"timestamp_level_start":1434211284},"37521":{"id":37521,"level":0,"players":1,"active_players":165,"clicks":null,"abilities":null,"status":3,"timestamp":1434211302,"timestamp_game_start":1434211302,"timestamp_level_start":1434211302},"37708":{"id":37708,"level":145,"players":1016,"active_players":261,"clicks":"3119503","abilities":"700","status":2,"timestamp":1434215280,"timestamp_game_start":1434213285,"timestamp_level_start":1434215278},"37701":{"id":37701,"level":150,"players":997,"active_players":205,"clicks":"3291604","abilities":"735","status":2,"timestamp":1434215280,"timestamp_game_start":1434213204,"timestamp_level_start":1434215265},"37742":{"id":37742,"level":123,"players":1019,"active_players":244,"clicks":"2715117","abilities":"574","status":2,"timestamp":1434215280,"timestamp_game_start":1434213619,"timestamp_level_start":1434215275},"37721":{"id":37721,"level":147,"players":1027,"active_players":254,"clicks":"3255651","abilities":"768","status":2,"timestamp":1434215280,"timestamp_game_start":1434213284,"timestamp_level_start":1434215270},"37842":{"id":37842,"level":2,"players":997,"active_players":488,"clicks":"95561","abilities":null,"status":2,"timestamp":1434215280,"timestamp_game_start":1434215190,"timestamp_level_start":1434215265},"37660":{"id":37660,"level":165,"players":1021,"active_players":237,"clicks":"3615659","abilities":"893","status":2,"timestamp":1434215280,"timestamp_game_start":1434212787,"timestamp_level_start":1434215264},"37796":{"id":37796,"level":66,"players":988,"active_players":360,"clicks":"1633794","abilities":"275","status":2,"timestamp":1434215280,"timestamp_game_start":1434214347,"timestamp_level_start":1434215277},"37784":{"id":37784,"level":80,"players":986,"active_players":334,"clicks":"1685387","abilities":"337","status":2,"timestamp":1434215279,"timestamp_game_start":1434214188,"timestamp_level_start":1434215265},"37764":{"id":37764,"level":109,"players":1017,"active_players":300,"clicks":"2209361","abilities":"572","status":2,"timestamp":1434215279,"timestamp_game_start":1434213784,"timestamp_level_start":1434215262},"37748":{"id":37748,"level":115,"players":1008,"active_players":234,"clicks":"2302144","abilities":"506","status":2,"timestamp":1434215279,"timestamp_game_start":1434213679,"timestamp_level_start":1434215263},"37551":{"id":37551,"level":0,"players":528,"active_players":44,"clicks":null,"abilities":null,"status":3,"timestamp":1434211267,"timestamp_game_start":1434211267,"timestamp_level_start":1434211267},"37558":{"id":37558,"level":869,"players":1500,"active_players":749,"clicks":"24155233","abilities":"6259","status":2,"timestamp":1434215279,"timestamp_game_start":1434211809,"timestamp_level_start":1434215271},"37618":{"id":37618,"level":265,"players":1040,"active_players":298,"clicks":"6091474","abilities":"1744","status":2,"timestamp":1434215279,"timestamp_game_start":1434212092,"timestamp_level_start":1434215277},"37657":{"id":37657,"level":242,"players":1028,"active_players":253,"clicks":"4867168","abilities":"1304","status":2,"timestamp":1434215279,"timestamp_game_start":1434212402,"timestamp_level_start":1434215264},"37765":{"id":37765,"level":112,"players":1016,"active_players":239,"clicks":"2398254","abilities":"597","status":2,"timestamp":1434215280,"timestamp_game_start":1434213660,"timestamp_level_start":1434215239},"37754":{"id":37754,"level":119,"players":1007,"active_players":281,"clicks":"2372963","abilities":"618","status":2,"timestamp":1434215279,"timestamp_game_start":1434213697,"timestamp_level_start":1434215267},"37699":{"id":37699,"level":154,"players":1016,"active_players":258,"clicks":"2854821","abilities":"806","status":2,"timestamp":1434215279,"timestamp_game_start":1434213279,"timestamp_level_start":1434215264},"37524":{"id":37524,"level":0,"players":0,"active_players":236,"clicks":null,"abilities":null,"status":3,"timestamp":1434211264,"timestamp_game_start":1434211264,"timestamp_level_start":1434211264},"37769":{"id":37769,"level":68,"players":1003,"active_players":355,"clicks":"1445741","abilities":"280","status":2,"timestamp":1434215280,"timestamp_game_start":1434214300,"timestamp_level_start":1434215271},"37526":{"id":37526,"level":0,"players":0,"active_players":0,"clicks":null,"abilities":null,"status":3,"timestamp":1434211616,"timestamp_game_start":1434211245,"timestamp_level_start":1434211245},"37508":{"id":37508,"level":23,"players":731,"active_players":408,"clicks":"631435","abilities":"58","status":3,"timestamp":1434211201,"timestamp_game_start":1434210691,"timestamp_level_start":1434211196},"37570":{"id":37570,"level":279,"players":1089,"active_players":314,"clicks":"629168508","abilities":"1755","status":2,"timestamp":1434215280,"timestamp_game_start":1434212119,"timestamp_level_start":1434215264},"37568":{"id":37568,"level":394,"players":1291,"active_players":471,"clicks":"9195442","abilities":"2907","status":2,"timestamp":1434215280,"timestamp_game_start":1434211837,"timestamp_level_start":1434215275},"37544":{"id":37544,"level":0,"players":0,"active_players":37,"clicks":null,"abilities":null,"status":3,"timestamp":1434211290,"timestamp_game_start":1434211290,"timestamp_level_start":1434211290},"37734":{"id":37734,"level":100,"players":1020,"active_players":266,"clicks":"2100214","abilities":"469","status":2,"timestamp":1434215280,"timestamp_game_start":1434213750,"timestamp_level_start":1434215264},"37601":{"id":37601,"level":383,"players":1125,"active_players":312,"clicks":"220960957647","abilities":"1904","status":2,"timestamp":1434215280,"timestamp_game_start":1434212066,"timestamp_level_start":1434215278},"37855":{"id":37855,"level":9,"players":1000,"active_players":543,"clicks":"312789","abilities":"11","status":2,"timestamp":1434215280,"timestamp_game_start":1434215072,"timestamp_level_start":1434215241},"37750":{"id":37750,"level":100,"players":1009,"active_players":281,"clicks":"2168744","abilities":"509","status":2,"timestamp":1434215280,"timestamp_game_start":1434213783,"timestamp_level_start":1434215275},"37525":{"id":37525,"level":0,"players":0,"active_players":119,"clicks":null,"abilities":null,"status":3,"timestamp":1434211301,"timestamp_game_start":1434211301,"timestamp_level_start":1434211301},"37736":{"id":37736,"level":114,"players":1017,"active_players":264,"clicks":"2396709","abilities":"542","status":2,"timestamp":1434215280,"timestamp_game_start":1434213693,"timestamp_level_start":1434215263},"37790":{"id":37790,"level":82,"players":991,"active_players":321,"clicks":"2013360","abilities":"308","status":2,"timestamp":1434215280,"timestamp_game_start":1434214177,"timestamp_level_start":1434215269},"37805":{"id":37805,"level":26,"players":1004,"active_players":477,"clicks":"618550","abilities":"66","status":2,"timestamp":1434215280,"timestamp_game_start":1434214841,"timestamp_level_start":1434215270},"37563":{"id":37563,"level":359,"players":1358,"active_players":465,"clicks":"8465897","abilities":"2796","status":2,"timestamp":1434215280,"timestamp_game_start":1434211834,"timestamp_level_start":1434215274},"37667":{"id":37667,"level":209,"players":1018,"active_players":263,"clicks":"4469081","abilities":"1328","status":2,"timestamp":1434215280,"timestamp_game_start":1434212689,"timestamp_level_start":1434215274},"37744":{"id":37744,"level":101,"players":1020,"active_players":280,"clicks":"2204438","abilities":"500","status":2,"timestamp":1434215280,"timestamp_game_start":1434213775,"timestamp_level_start":1434215273},"37567":{"id":37567,"level":443,"players":1500,"active_players":557,"clicks":"206727070","abilities":"3334","status":2,"timestamp":1434215280,"timestamp_game_start":1434211818,"timestamp_level_start":1434215279},"37600":{"id":37600,"level":383,"players":1172,"active_players":402,"clicks":"9743114","abilities":"2523","status":2,"timestamp":1434215280,"timestamp_game_start":1434211981,"timestamp_level_start":1434215273},"37673":{"id":37673,"level":187,"players":1031,"active_players":250,"clicks":"4037204","abilities":"1099","status":2,"timestamp":1434215280,"timestamp_game_start":1434212746,"timestamp_level_start":1434215276},"37593":{"id":37593,"level":327,"players":1138,"active_players":347,"clicks":"9699668","abilities":"1998","status":2,"timestamp":1434215280,"timestamp_game_start":1434212049,"timestamp_level_start":1434215276},"37531":{"id":37531,"level":0,"players":0,"active_players":40,"clicks":null,"abilities":null,"status":3,"timestamp":1434211253,"timestamp_game_start":1434211253,"timestamp_level_start":1434211253},"37655":{"id":37655,"level":229,"players":1036,"active_players":243,"clicks":"4815104","abilities":"1415","status":2,"timestamp":1434215280,"timestamp_game_start":1434212378,"timestamp_level_start":1434215263},"37608":{"id":37608,"level":310,"players":1110,"active_players":320,"clicks":"6769257","abilities":"1774","status":2,"timestamp":1434215280,"timestamp_game_start":1434212105,"timestamp_level_start":1434215269},"37636":{"id":37636,"level":223,"players":1045,"active_players":268,"clicks":"4758565","abilities":"1339","status":2,"timestamp":1434215280,"timestamp_game_start":1434212448,"timestamp_level_start":1434215268},"37719":{"id":37719,"level":149,"players":1013,"active_players":210,"clicks":"3313200","abilities":"645","status":2,"timestamp":1434215280,"timestamp_game_start":1434213203,"timestamp_level_start":1434215267},"37733":{"id":37733,"level":114,"players":1010,"active_players":265,"clicks":"2575299","abilities":"546","status":2,"timestamp":1434215280,"timestamp_game_start":1434213758,"timestamp_level_start":1434215280},"37707":{"id":37707,"level":171,"players":1140,"active_players":298,"clicks":"4061724","abilities":"860","status":2,"timestamp":1434215280,"timestamp_game_start":1434213234,"timestamp_level_start":1434215262},"37759":{"id":37759,"level":120,"players":1016,"active_players":254,"clicks":"2806691","abilities":"597","status":2,"timestamp":1434215280,"timestamp_game_start":1434213503,"timestamp_level_start":1434215265},"37756":{"id":37756,"level":105,"players":1009,"active_players":267,"clicks":"2300230","abilities":"508","status":2,"timestamp":1434215280,"timestamp_game_start":1434213780,"timestamp_level_start":1434215273},"37776":{"id":37776,"level":90,"players":1005,"active_players":328,"clicks":"1904994","abilities":"360","status":2,"timestamp":1434215280,"timestamp_game_start":1434214139,"timestamp_level_start":1434215279},"37634":{"id":37634,"level":219,"players":1040,"active_players":241,"clicks":"5065356","abilities":"1347","status":2,"timestamp":1434215280,"timestamp_game_start":1434212390,"timestamp_level_start":1434215237},"37670":{"id":37670,"level":184,"players":1029,"active_players":243,"clicks":"3868410","abilities":"1065","status":2,"timestamp":1434215280,"timestamp_game_start":1434212763,"timestamp_level_start":1434215262},"37865":{"id":37865,"level":4,"players":989,"active_players":516,"clicks":"101038","abilities":"2","status":2,"timestamp":1434215280,"timestamp_game_start":1434215170,"timestamp_level_start":1434215277},"37820":{"id":37820,"level":38,"players":1000,"active_players":473,"clicks":"811287","abilities":"94","status":2,"timestamp":1434215280,"timestamp_game_start":1434214710,"timestamp_level_start":1434215271},"37835":{"id":37835,"level":46,"players":1006,"active_players":451,"clicks":"1028472","abilities":"133","status":2,"timestamp":1434215280,"timestamp_game_start":1434214651,"timestamp_level_start":1434215275},"37799":{"id":37799,"level":79,"players":1019,"active_players":332,"clicks":"1631526","abilities":"353","status":2,"timestamp":1434215280,"timestamp_game_start":1434214145,"timestamp_level_start":1434215280},"37844":{"id":37844,"level":6,"players":1006,"active_players":549,"clicks":"190284","abilities":"4","status":2,"timestamp":1434215280,"timestamp_game_start":1434215125,"timestamp_level_start":1434215270},"37675":{"id":37675,"level":163,"players":1051,"active_players":234,"clicks":"4391248","abilities":"961","status":2,"timestamp":1434215280,"timestamp_game_start":1434212778,"timestamp_level_start":1434215269},"37823":{"id":37823,"level":26,"players":1001,"active_players":492,"clicks":"660080","abilities":"52","status":2,"timestamp":1434215280,"timestamp_game_start":1434214844,"timestamp_level_start":1434215277},"37720":{"id":37720,"level":117,"players":1026,"active_players":202,"clicks":"2262398","abilities":"613","status":2,"timestamp":1434215280,"timestamp_game_start":1434213316,"timestamp_level_start":1434215273},"37811":{"id":37811,"level":51,"players":998,"active_players":427,"clicks":"1199463","abilities":"165","status":2,"timestamp":1434215280,"timestamp_game_start":1434214592,"timestamp_level_start":1434215275},"37797":{"id":37797,"level":71,"players":1005,"active_players":357,"clicks":"1911027","abilities":"283","status":2,"timestamp":1434215280,"timestamp_game_start":1434214309,"timestamp_level_start":1434215274},"37614":{"id":37614,"level":249,"players":1118,"active_players":285,"clicks":"6382374","abilities":"1596","status":2,"timestamp":1434215280,"timestamp_game_start":1434212047,"timestamp_level_start":1434215238},"37807":{"id":37807,"level":33,"players":1002,"active_players":463,"clicks":"928838","abilities":"66","status":2,"timestamp":1434215280,"timestamp_game_start":1434214792,"timestamp_level_start":1434215273},"37834":{"id":37834,"level":41,"players":990,"active_players":465,"clicks":"942303","abilities":"107","status":2,"timestamp":1434215280,"timestamp_game_start":1434214709,"timestamp_level_start":1434215275},"37647":{"id":37647,"level":228,"players":1053,"active_players":249,"clicks":"4794601","abilities":"1365","status":2,"timestamp":1434215280,"timestamp_game_start":1434212396,"timestamp_level_start":1434215269},"37605":{"id":37605,"level":264,"players":1099,"active_players":297,"clicks":"5255747","abilities":"1737","status":2,"timestamp":1434215280,"timestamp_game_start":1434212090,"timestamp_level_start":1434215268},"37510":{"id":37510,"level":0,"players":0,"active_players":39,"clicks":null,"abilities":null,"status":3,"timestamp":1434211231,"timestamp_game_start":1434211231,"timestamp_level_start":1434211231},"37763":{"id":37763,"level":117,"players":1012,"active_players":233,"clicks":"2461668","abilities":"546","status":2,"timestamp":1434215280,"timestamp_game_start":1434213629,"timestamp_level_start":1434215249},"37559":{"id":37559,"level":875,"players":1500,"active_players":879,"clicks":"24952229331","abilities":"7166","status":2,"timestamp":1434215280,"timestamp_game_start":1434211782,"timestamp_level_start":1434215279},"37718":{"id":37718,"level":137,"players":1004,"active_players":213,"clicks":"2641822","abilities":"649","status":2,"timestamp":1434215280,"timestamp_game_start":1434213235,"timestamp_level_start":1434215268},"37631":{"id":37631,"level":269,"players":1065,"active_players":272,"clicks":"5544538","abilities":"1488","status":2,"timestamp":1434215280,"timestamp_game_start":1434212302,"timestamp_level_start":1434215274},"37684":{"id":37684,"level":177,"players":1021,"active_players":242,"clicks":"4054476","abilities":"929","status":2,"timestamp":1434215280,"timestamp_game_start":1434212858,"timestamp_level_start":1434215278},"37696":{"id":37696,"level":165,"players":1019,"active_players":266,"clicks":"3545943","abilities":"830","status":2,"timestamp":1434215280,"timestamp_game_start":1434213212,"timestamp_level_start":1434215275},"37821":{"id":37821,"level":33,"players":1009,"active_players":476,"clicks":"816481","abilities":"69","status":2,"timestamp":1434215280,"timestamp_game_start":1434214789,"timestamp_level_start":1434215273},"37873":{"id":37873,"level":7,"players":999,"active_players":545,"clicks":"203142","abilities":"5","status":2,"timestamp":1434215280,"timestamp_game_start":1434215117,"timestamp_level_start":1434215277},"37727":{"id":37727,"level":133,"players":1021,"active_players":203,"clicks":"2821648","abilities":"692","status":2,"timestamp":1434215280,"timestamp_game_start":1434213162,"timestamp_level_start":1434215265},"37868":{"id":37868,"level":0,"players":1000,"active_players":107,"clicks":"1649","abilities":null,"status":2,"timestamp":1434215280,"timestamp_game_start":1434215271,"timestamp_level_start":1434215271},"37848":{"id":37848,"level":12,"players":992,"active_players":529,"clicks":"378538","abilities":"23","status":2,"timestamp":1434215280,"timestamp_game_start":1434215040,"timestamp_level_start":1434215274},"37831":{"id":37831,"level":47,"players":1006,"active_players":396,"clicks":"1415780","abilities":"140","status":2,"timestamp":1434215280,"timestamp_game_start":1434214556,"timestamp_level_start":1434215277},"37603":{"id":37603,"level":346,"players":1147,"active_players":367,"clicks":"7712397","abilities":"2317","status":2,"timestamp":1434215280,"timestamp_game_start":1434212063,"timestamp_level_start":1434215270},"37668":{"id":37668,"level":175,"players":1043,"active_players":220,"clicks":"3737721","abilities":"972","status":2,"timestamp":1434215280,"timestamp_game_start":1434212733,"timestamp_level_start":1434215272},"37505":{"id":37505,"level":0,"players":0,"active_players":36,"clicks":null,"abilities":null,"status":3,"timestamp":1434211244,"timestamp_game_start":1434211244,"timestamp_level_start":1434211244},"37775":{"id":37775,"level":91,"players":1006,"active_players":332,"clicks":"1823763","abilities":"427","status":2,"timestamp":1434215280,"timestamp_game_start":1434214064,"timestamp_level_start":1434215279},"37874":{"id":37874,"level":6,"players":1004,"active_players":576,"clicks":"174069","abilities":"4","status":2,"timestamp":1434215281,"timestamp_game_start":1434215129,"timestamp_level_start":1434215273},"37552":{"id":37552,"level":459,"players":1500,"active_players":573,"clicks":"13319604","abilities":"3476","status":2,"timestamp":1434215280,"timestamp_game_start":1434211820,"timestamp_level_start":1434215271},"37771":{"id":37771,"level":69,"players":1014,"active_players":330,"clicks":"1683392","abilities":"278","status":2,"timestamp":1434215281,"timestamp_game_start":1434214266,"timestamp_level_start":1434215265},"37654":{"id":37654,"level":219,"players":1055,"active_players":256,"clicks":"4687486","abilities":"1325","status":2,"timestamp":1434215282,"timestamp_game_start":1434212397,"timestamp_level_start":1434215248},"37693":{"id":37693,"level":198,"players":1039,"active_players":255,"clicks":"7063827","abilities":"1032","status":2,"timestamp":1434215282,"timestamp_game_start":1434212793,"timestamp_level_start":1434215272}}